{
"meta":{"test_sets":[],"test_metrics":[],"learn_metrics":[{"best_value":"Min","name":"Logloss"}],"launch_mode":"Train","parameters":"","iteration_count":1000,"learn_sets":["learn"],"name":"experiment"},
"iterations":[
{"learn":[0.6639391562],"iteration":0,"passed_time":0.06319098502,"remaining_time":63.12779404},
{"learn":[0.6388212128],"iteration":1,"passed_time":0.06769546045,"remaining_time":33.78003476},
{"learn":[0.6132715794],"iteration":2,"passed_time":0.07164066278,"remaining_time":23.80858026},
{"learn":[0.5916785972],"iteration":3,"passed_time":0.07663178871,"remaining_time":19.08131539},
{"learn":[0.5713598108],"iteration":4,"passed_time":0.08114918037,"remaining_time":16.14868689},
{"learn":[0.5521125482],"iteration":5,"passed_time":0.08622459517,"remaining_time":14.28454127},
{"learn":[0.5338417814],"iteration":6,"passed_time":0.0905072863,"remaining_time":12.83910504},
{"learn":[0.517316322],"iteration":7,"passed_time":0.09434649215,"remaining_time":11.69896503},
{"learn":[0.5026573556],"iteration":8,"passed_time":0.09834902591,"remaining_time":10.82932052},
{"learn":[0.4886832956],"iteration":9,"passed_time":0.1029483315,"remaining_time":10.19188482},
{"learn":[0.4762173496],"iteration":10,"passed_time":0.1071151932,"remaining_time":9.630629639},
{"learn":[0.4644441396],"iteration":11,"passed_time":0.1109963976,"remaining_time":9.138703403},
{"learn":[0.4545356708],"iteration":12,"passed_time":0.1152305903,"remaining_time":8.748660974},
{"learn":[0.4448380596],"iteration":13,"passed_time":0.1193759944,"remaining_time":8.407480745},
{"learn":[0.437207858],"iteration":14,"passed_time":0.1245942377,"remaining_time":8.181688279},
{"learn":[0.4303555361],"iteration":15,"passed_time":0.1290729224,"remaining_time":7.937984725},
{"learn":[0.422649306],"iteration":16,"passed_time":0.1337206847,"remaining_time":7.732201944},
{"learn":[0.4152636011],"iteration":17,"passed_time":0.1379848348,"remaining_time":7.527839319},
{"learn":[0.4084674515],"iteration":18,"passed_time":0.1423551063,"remaining_time":7.35001891},
{"learn":[0.4021900213],"iteration":19,"passed_time":0.1480946241,"remaining_time":7.256636579},
{"learn":[0.3965373259],"iteration":20,"passed_time":0.1531091659,"remaining_time":7.137803495},
{"learn":[0.3912345909],"iteration":21,"passed_time":0.1571472401,"remaining_time":6.985909129},
{"learn":[0.386120545],"iteration":22,"passed_time":0.1613080603,"remaining_time":6.852085866},
{"learn":[0.3821610268],"iteration":23,"passed_time":0.1651681405,"remaining_time":6.716837712},
{"learn":[0.3776558637],"iteration":24,"passed_time":0.1691240508,"remaining_time":6.59583798},
{"learn":[0.3735522144],"iteration":25,"passed_time":0.1742820878,"remaining_time":6.528875136},
{"learn":[0.3697142252],"iteration":26,"passed_time":0.1785144889,"remaining_time":6.43313325},
{"learn":[0.3659681012],"iteration":27,"passed_time":0.182608478,"remaining_time":6.339122879},
{"learn":[0.3625398382],"iteration":28,"passed_time":0.1879412176,"remaining_time":6.292790423},
{"learn":[0.359070365],"iteration":29,"passed_time":0.1920743303,"remaining_time":6.210403348},
{"learn":[0.3561098934],"iteration":30,"passed_time":0.1961536532,"remaining_time":6.131383548},
{"learn":[0.3539820127],"iteration":31,"passed_time":0.1998791128,"remaining_time":6.046343164},
{"learn":[0.3508339485],"iteration":32,"passed_time":0.2041740119,"remaining_time":5.982917258},
{"learn":[0.3481219646],"iteration":33,"passed_time":0.207986177,"remaining_time":5.909254322},
{"learn":[0.3455353298],"iteration":34,"passed_time":0.2122799511,"remaining_time":5.852861508},
{"learn":[0.343377683],"iteration":35,"passed_time":0.2160216185,"remaining_time":5.784578895},
{"learn":[0.3411286635],"iteration":36,"passed_time":0.2200869835,"remaining_time":5.728209868},
{"learn":[0.3392777544],"iteration":37,"passed_time":0.2239907705,"remaining_time":5.670503191},
{"learn":[0.3375166202],"iteration":38,"passed_time":0.2279462225,"remaining_time":5.616828714},
{"learn":[0.3352096574],"iteration":39,"passed_time":0.2321008762,"remaining_time":5.57042103},
{"learn":[0.333879801],"iteration":40,"passed_time":0.2362262809,"remaining_time":5.525390327},
{"learn":[0.33201832],"iteration":41,"passed_time":0.241091661,"remaining_time":5.499185982},
{"learn":[0.3307691673],"iteration":42,"passed_time":0.2468760523,"remaining_time":5.494427489},
{"learn":[0.3290102225],"iteration":43,"passed_time":0.2518568452,"remaining_time":5.472162364},
{"learn":[0.3279829426],"iteration":44,"passed_time":0.256500191,"remaining_time":5.443504054},
{"learn":[0.3268006318],"iteration":45,"passed_time":0.2614038199,"remaining_time":5.421287916},
{"learn":[0.3257055837],"iteration":46,"passed_time":0.265736926,"remaining_time":5.388240223},
{"learn":[0.3243963068],"iteration":47,"passed_time":0.2703787302,"remaining_time":5.362511482},
{"learn":[0.3231560088],"iteration":48,"passed_time":0.2746117563,"remaining_time":5.329709801},
{"learn":[0.322099766],"iteration":49,"passed_time":0.2800032023,"remaining_time":5.320060843},
{"learn":[0.3211130857],"iteration":50,"passed_time":0.2847905433,"remaining_time":5.299337757},
{"learn":[0.3195788147],"iteration":51,"passed_time":0.2894185146,"remaining_time":5.276322151},
{"learn":[0.3184334888],"iteration":52,"passed_time":0.2937584122,"remaining_time":5.248853138},
{"learn":[0.3173569681],"iteration":53,"passed_time":0.2981226006,"remaining_time":5.222666299},
{"learn":[0.3161119056],"iteration":54,"passed_time":0.3027022402,"remaining_time":5.200974854},
{"learn":[0.3153326156],"iteration":55,"passed_time":0.3074216668,"remaining_time":5.182250955},
{"learn":[0.3144104731],"iteration":56,"passed_time":0.3122323404,"remaining_time":5.165528018},
{"learn":[0.313253625],"iteration":57,"passed_time":0.3173026304,"remaining_time":5.153432376},
{"learn":[0.312720902],"iteration":58,"passed_time":0.3218971445,"remaining_time":5.13398666},
{"learn":[0.3119535965],"iteration":59,"passed_time":0.3261917935,"remaining_time":5.110338099},
{"learn":[0.3111082274],"iteration":60,"passed_time":0.3312880826,"remaining_time":5.099664092},
{"learn":[0.3103993993],"iteration":61,"passed_time":0.3367458597,"remaining_time":5.094638975},
{"learn":[0.3098412158],"iteration":62,"passed_time":0.3433394741,"remaining_time":5.106493449},
{"learn":[0.3091524149],"iteration":63,"passed_time":0.3491129491,"remaining_time":5.10577688},
{"learn":[0.3084238693],"iteration":64,"passed_time":0.3622564293,"remaining_time":5.210919406},
{"learn":[0.3077504106],"iteration":65,"passed_time":0.371722865,"remaining_time":5.260441756},
{"learn":[0.3071833419],"iteration":66,"passed_time":0.3875887548,"remaining_time":5.397318033},
{"learn":[0.3064495908],"iteration":67,"passed_time":0.3939174613,"remaining_time":5.398986382},
{"learn":[0.3055552273],"iteration":68,"passed_time":0.3999733852,"remaining_time":5.396742343},
{"learn":[0.3046419881],"iteration":69,"passed_time":0.4055580748,"remaining_time":5.388128708},
{"learn":[0.3037851066],"iteration":70,"passed_time":0.4106871961,"remaining_time":5.37363951},
{"learn":[0.3032770817],"iteration":71,"passed_time":0.416853283,"remaining_time":5.372775648},
{"learn":[0.3023473421],"iteration":72,"passed_time":0.422796419,"remaining_time":5.368935349},
{"learn":[0.3017864581],"iteration":73,"passed_time":0.428961506,"remaining_time":5.367815602},
{"learn":[0.301277709],"iteration":74,"passed_time":0.4362797213,"remaining_time":5.380783229},
{"learn":[0.3007547774],"iteration":75,"passed_time":0.4424753489,"remaining_time":5.379568716},
{"learn":[0.3001498235],"iteration":76,"passed_time":0.4490666717,"remaining_time":5.382968026},
{"learn":[0.2994078774],"iteration":77,"passed_time":0.4553085061,"remaining_time":5.381980034},
{"learn":[0.2987376571],"iteration":78,"passed_time":0.4621822779,"remaining_time":5.388226303},
{"learn":[0.2982725789],"iteration":79,"passed_time":0.4689995931,"remaining_time":5.393495321},
{"learn":[0.2978629177],"iteration":80,"passed_time":0.4765987158,"remaining_time":5.407336047},
{"learn":[0.2973715263],"iteration":81,"passed_time":0.4868372092,"remaining_time":5.450201927},
{"learn":[0.2965599706],"iteration":82,"passed_time":0.4958413685,"remaining_time":5.478151023},
{"learn":[0.2961178495],"iteration":83,"passed_time":0.5045172471,"remaining_time":5.501640456},
{"learn":[0.2956623093],"iteration":84,"passed_time":0.5141101369,"remaining_time":5.534244415},
{"learn":[0.2950775105],"iteration":85,"passed_time":0.5227258091,"remaining_time":5.555481274},
{"learn":[0.2946021849],"iteration":86,"passed_time":0.5314308117,"remaining_time":5.576969323},
{"learn":[0.2942396145],"iteration":87,"passed_time":0.5390689331,"remaining_time":5.586714398},
{"learn":[0.2938082163],"iteration":88,"passed_time":0.5475322354,"remaining_time":5.604515353},
{"learn":[0.2931076971],"iteration":89,"passed_time":0.5554768049,"remaining_time":5.616487694},
{"learn":[0.2926025305],"iteration":90,"passed_time":0.5638445687,"remaining_time":5.632249593},
{"learn":[0.2920822323],"iteration":91,"passed_time":0.5718036378,"remaining_time":5.643453295},
{"learn":[0.2915519562],"iteration":92,"passed_time":0.5804596837,"remaining_time":5.661042291},
{"learn":[0.2909317671],"iteration":93,"passed_time":0.5966683955,"remaining_time":5.750867727},
{"learn":[0.2903802389],"iteration":94,"passed_time":0.6075431594,"remaining_time":5.787647992},
{"learn":[0.2900542165],"iteration":95,"passed_time":0.6168085184,"remaining_time":5.808280215},
{"learn":[0.2895846385],"iteration":96,"passed_time":0.6240192373,"remaining_time":5.809168776},
{"learn":[0.2888940988],"iteration":97,"passed_time":0.6320068887,"remaining_time":5.817042996},
{"learn":[0.2885536217],"iteration":98,"passed_time":0.6397586313,"remaining_time":5.822449766},
{"learn":[0.288163362],"iteration":99,"passed_time":0.6481056041,"remaining_time":5.832950437},
{"learn":[0.2876911768],"iteration":100,"passed_time":0.6560850058,"remaining_time":5.839806141},
{"learn":[0.2874449601],"iteration":101,"passed_time":0.6634193873,"remaining_time":5.840692253},
{"learn":[0.2869046916],"iteration":102,"passed_time":0.6708800979,"remaining_time":5.842518911},
{"learn":[0.2865767836],"iteration":103,"passed_time":0.6789820372,"remaining_time":5.849691397},
{"learn":[0.2861188277],"iteration":104,"passed_time":0.6868127771,"remaining_time":5.854261291},
{"learn":[0.2855144357],"iteration":105,"passed_time":0.69731647,"remaining_time":5.881140794},
{"learn":[0.2849224126],"iteration":106,"passed_time":0.7040566629,"remaining_time":5.875912149},
{"learn":[0.2846164012],"iteration":107,"passed_time":0.7104728665,"remaining_time":5.867979601},
{"learn":[0.2843753228],"iteration":108,"passed_time":0.715947518,"remaining_time":5.852378336},
{"learn":[0.2839373143],"iteration":109,"passed_time":0.7217864908,"remaining_time":5.83990888},
{"learn":[0.2835680466],"iteration":110,"passed_time":0.7278722471,"remaining_time":5.829535384},
{"learn":[0.283072772],"iteration":111,"passed_time":0.7335134764,"remaining_time":5.815713992},
{"learn":[0.2827472944],"iteration":112,"passed_time":0.739791018,"remaining_time":5.80703215},
{"learn":[0.2824598594],"iteration":113,"passed_time":0.7458065682,"remaining_time":5.796356311},
{"learn":[0.2819745764],"iteration":114,"passed_time":0.7516036257,"remaining_time":5.784080076},
{"learn":[0.2815319166],"iteration":115,"passed_time":0.7573315605,"remaining_time":5.771388789},
{"learn":[0.2812924117],"iteration":116,"passed_time":0.7634095254,"remaining_time":5.761458213},
{"learn":[0.2810350892],"iteration":117,"passed_time":0.7691085028,"remaining_time":5.748760165},
{"learn":[0.280679621],"iteration":118,"passed_time":0.7749222264,"remaining_time":5.737029256},
{"learn":[0.2803628424],"iteration":119,"passed_time":0.7804105858,"remaining_time":5.723010963},
{"learn":[0.2799763261],"iteration":120,"passed_time":0.7860890223,"remaining_time":5.710514468},
{"learn":[0.2795955495],"iteration":121,"passed_time":0.7931304135,"remaining_time":5.707938549},
{"learn":[0.2792157267],"iteration":122,"passed_time":0.8002049702,"remaining_time":5.705526495},
{"learn":[0.2787781372],"iteration":123,"passed_time":0.8058826983,"remaining_time":5.69317132},
{"learn":[0.2785253475],"iteration":124,"passed_time":0.812066493,"remaining_time":5.684465451},
{"learn":[0.2781104551],"iteration":125,"passed_time":0.8176866814,"remaining_time":5.671890155},
{"learn":[0.2777548753],"iteration":126,"passed_time":0.823611568,"remaining_time":5.661518888},
{"learn":[0.2773996996],"iteration":127,"passed_time":0.8286411926,"remaining_time":5.645118125},
{"learn":[0.2771626364],"iteration":128,"passed_time":0.8335087393,"remaining_time":5.627799317},
{"learn":[0.2765292428],"iteration":129,"passed_time":0.838688734,"remaining_time":5.612763066},
{"learn":[0.2762513237],"iteration":130,"passed_time":0.8435865713,"remaining_time":5.596005576},
{"learn":[0.2759565288],"iteration":131,"passed_time":0.8482931651,"remaining_time":5.578170207},
{"learn":[0.2755808526],"iteration":132,"passed_time":0.8531602118,"remaining_time":5.561578223},
{"learn":[0.2752834692],"iteration":133,"passed_time":0.8580984228,"remaining_time":5.54562115},
{"learn":[0.2749568187],"iteration":134,"passed_time":0.8641298892,"remaining_time":5.536832253},
{"learn":[0.2747124569],"iteration":135,"passed_time":0.8695665003,"remaining_time":5.524304826},
{"learn":[0.2743174554],"iteration":136,"passed_time":0.8756944218,"remaining_time":5.516235665},
{"learn":[0.2738938361],"iteration":137,"passed_time":0.8804056821,"remaining_time":5.499345637},
{"learn":[0.2735783282],"iteration":138,"passed_time":0.8856030928,"remaining_time":5.485642179},
{"learn":[0.2733178807],"iteration":139,"passed_time":0.8910608699,"remaining_time":5.47365963},
{"learn":[0.2729960861],"iteration":140,"passed_time":0.8960279967,"remaining_time":5.45878049},
{"learn":[0.2726463965],"iteration":141,"passed_time":0.9024188261,"remaining_time":5.45264333},
{"learn":[0.2717729568],"iteration":142,"passed_time":0.9077248166,"remaining_time":5.440001174},
{"learn":[0.2715081153],"iteration":143,"passed_time":0.9121855851,"remaining_time":5.422436534},
{"learn":[0.2713078048],"iteration":144,"passed_time":0.9171127132,"remaining_time":5.40780255},
{"learn":[0.2710944571],"iteration":145,"passed_time":0.9221578373,"remaining_time":5.393991733},
{"learn":[0.2707107942],"iteration":146,"passed_time":0.9276526132,"remaining_time":5.382909381},
{"learn":[0.2704960209],"iteration":147,"passed_time":0.9324363294,"remaining_time":5.367809139},
{"learn":[0.2702590049],"iteration":148,"passed_time":0.9374978279,"remaining_time":5.354433903},
{"learn":[0.2699183378],"iteration":149,"passed_time":0.9423453336,"remaining_time":5.339956891},
{"learn":[0.2696026954],"iteration":150,"passed_time":0.9470765932,"remaining_time":5.324953825},
{"learn":[0.2694066879],"iteration":151,"passed_time":0.9517507713,"remaining_time":5.309767461},
{"learn":[0.2691674538],"iteration":152,"passed_time":0.9567124399,"remaining_time":5.296310043},
{"learn":[0.2686753531],"iteration":153,"passed_time":0.9613422862,"remaining_time":5.281140092},
{"learn":[0.268409911],"iteration":154,"passed_time":0.9658178876,"remaining_time":5.265265258},
{"learn":[0.2680987604],"iteration":155,"passed_time":0.9704399424,"remaining_time":5.250328919},
{"learn":[0.2677795866],"iteration":156,"passed_time":0.9756968512,"remaining_time":5.238932774},
{"learn":[0.2675050069],"iteration":157,"passed_time":0.9803045732,"remaining_time":5.224154751},
{"learn":[0.2673669615],"iteration":158,"passed_time":0.9858603887,"remaining_time":5.214519414},
{"learn":[0.2671853749],"iteration":159,"passed_time":0.9914825353,"remaining_time":5.205283311},
{"learn":[0.2669170603],"iteration":160,"passed_time":0.9967976922,"remaining_time":5.194492321},
{"learn":[0.2665060226],"iteration":161,"passed_time":1.001875732,"remaining_time":5.182542366},
{"learn":[0.2661502755],"iteration":162,"passed_time":1.008276936,"remaining_time":5.177471138},
{"learn":[0.2658401372],"iteration":163,"passed_time":1.012922615,"remaining_time":5.163434794},
{"learn":[0.2655244434],"iteration":164,"passed_time":1.017888575,"remaining_time":5.151133093},
{"learn":[0.2652643785],"iteration":165,"passed_time":1.023198566,"remaining_time":5.140648215},
{"learn":[0.2650444027],"iteration":166,"passed_time":1.028537263,"remaining_time":5.130368505},
{"learn":[0.2648424697],"iteration":167,"passed_time":1.033883127,"remaining_time":5.120183107},
{"learn":[0.264471704],"iteration":168,"passed_time":1.039933593,"remaining_time":5.113519621},
{"learn":[0.2641292395],"iteration":169,"passed_time":1.045271833,"remaining_time":5.103386006},
{"learn":[0.2638566317],"iteration":170,"passed_time":1.050827731,"remaining_time":5.09436368},
{"learn":[0.2636024977],"iteration":171,"passed_time":1.05674666,"remaining_time":5.08712927},
{"learn":[0.2631923238],"iteration":172,"passed_time":1.061943737,"remaining_time":5.076459368},
{"learn":[0.2629146269],"iteration":173,"passed_time":1.067717046,"remaining_time":5.068587814},
{"learn":[0.2627432566],"iteration":174,"passed_time":1.073318276,"remaining_time":5.059929017},
{"learn":[0.2624738189],"iteration":175,"passed_time":1.07872518,"remaining_time":5.050395161},
{"learn":[0.2622382798],"iteration":176,"passed_time":1.084139459,"remaining_time":5.040942228},
{"learn":[0.2617885812],"iteration":177,"passed_time":1.089744022,"remaining_time":5.032413407},
{"learn":[0.2615416307],"iteration":178,"passed_time":1.094383285,"remaining_time":5.019489816},
{"learn":[0.2613670167],"iteration":179,"passed_time":1.099152502,"remaining_time":5.007250286},
{"learn":[0.26097947],"iteration":180,"passed_time":1.104346538,"remaining_time":4.997015549},
{"learn":[0.2606503113],"iteration":181,"passed_time":1.111143729,"remaining_time":4.994041593},
{"learn":[0.2602994374],"iteration":182,"passed_time":1.11707049,"remaining_time":4.987139838},
{"learn":[0.260073717],"iteration":183,"passed_time":1.123318283,"remaining_time":4.981672384},
{"learn":[0.2597483383],"iteration":184,"passed_time":1.12942758,"remaining_time":4.975586365},
{"learn":[0.2595974971],"iteration":185,"passed_time":1.134153423,"remaining_time":4.963445625},
{"learn":[0.2592668136],"iteration":186,"passed_time":1.14017014,"remaining_time":4.956996383},
{"learn":[0.2590139404],"iteration":187,"passed_time":1.145455506,"remaining_time":4.94739293},
{"learn":[0.25872035],"iteration":188,"passed_time":1.151010488,"remaining_time":4.938992094},
{"learn":[0.2585065519],"iteration":189,"passed_time":1.156328187,"remaining_time":4.929609637},
{"learn":[0.2581882836],"iteration":190,"passed_time":1.160951658,"remaining_time":4.917329274},
{"learn":[0.2576799655],"iteration":191,"passed_time":1.166253607,"remaining_time":4.907983929},
{"learn":[0.2573821375],"iteration":192,"passed_time":1.172543565,"remaining_time":4.902811693},
{"learn":[0.2572486181],"iteration":193,"passed_time":1.17716437,"remaining_time":4.890693206},
{"learn":[0.2569576225],"iteration":194,"passed_time":1.182423903,"remaining_time":4.881288421},
{"learn":[0.2568081075],"iteration":195,"passed_time":1.187515359,"remaining_time":4.871236474},
{"learn":[0.2563621139],"iteration":196,"passed_time":1.193034593,"remaining_time":4.862978568},
{"learn":[0.2561258217],"iteration":197,"passed_time":1.198953563,"remaining_time":4.856367461},
{"learn":[0.2559336238],"iteration":198,"passed_time":1.204631124,"remaining_time":4.848791611},
{"learn":[0.2557721532],"iteration":199,"passed_time":1.211484563,"remaining_time":4.845938253},
{"learn":[0.2555145327],"iteration":200,"passed_time":1.217638026,"remaining_time":4.8402626},
{"learn":[0.2551920325],"iteration":201,"passed_time":1.224119102,"remaining_time":4.835876453},
{"learn":[0.2547513002],"iteration":202,"passed_time":1.230179609,"remaining_time":4.829818466},
{"learn":[0.254324357],"iteration":203,"passed_time":1.236405277,"remaining_time":4.824404906},
{"learn":[0.2540652379],"iteration":204,"passed_time":1.242430119,"remaining_time":4.818204608},
{"learn":[0.2538791332],"iteration":205,"passed_time":1.24831084,"remaining_time":4.811450521},
{"learn":[0.2535374728],"iteration":206,"passed_time":1.255193737,"remaining_time":4.808544123},
{"learn":[0.2532311091],"iteration":207,"passed_time":1.261331825,"remaining_time":4.802763487},
{"learn":[0.2530873055],"iteration":208,"passed_time":1.266715854,"remaining_time":4.794125554},
{"learn":[0.25286165],"iteration":209,"passed_time":1.272605659,"remaining_time":4.787421288},
{"learn":[0.2526281338],"iteration":210,"passed_time":1.278449506,"remaining_time":4.780552893},
{"learn":[0.2524364601],"iteration":211,"passed_time":1.28399953,"remaining_time":4.772602028},
{"learn":[0.2522467962],"iteration":212,"passed_time":1.28958972,"remaining_time":4.76482211},
{"learn":[0.2521015373],"iteration":213,"passed_time":1.295134119,"remaining_time":4.756894474},
{"learn":[0.2520060751],"iteration":214,"passed_time":1.300388945,"remaining_time":4.747931728},
{"learn":[0.2517719916],"iteration":215,"passed_time":1.306227584,"remaining_time":4.741122342},
{"learn":[0.2516365405],"iteration":216,"passed_time":1.31176215,"remaining_time":4.733224717},
{"learn":[0.2514958593],"iteration":217,"passed_time":1.318750001,"remaining_time":4.730561932},
{"learn":[0.2511921069],"iteration":218,"passed_time":1.32460364,"remaining_time":4.723814809},
{"learn":[0.2508432586],"iteration":219,"passed_time":1.329981629,"remaining_time":4.71538941},
{"learn":[0.25061138],"iteration":220,"passed_time":1.348117485,"remaining_time":4.751961631},
{"learn":[0.250454158],"iteration":221,"passed_time":1.362609962,"remaining_time":4.775272749},
{"learn":[0.250315799],"iteration":222,"passed_time":1.385605573,"remaining_time":4.827872333},
{"learn":[0.2502114803],"iteration":223,"passed_time":1.40543254,"remaining_time":4.86881987},
{"learn":[0.2500131914],"iteration":224,"passed_time":1.416256722,"remaining_time":4.878217598},
{"learn":[0.2497695088],"iteration":225,"passed_time":1.423356986,"remaining_time":4.874682776},
{"learn":[0.24965056],"iteration":226,"passed_time":1.429758774,"remaining_time":4.868738027},
{"learn":[0.2494920137],"iteration":227,"passed_time":1.435871612,"remaining_time":4.861810898},
{"learn":[0.2493323607],"iteration":228,"passed_time":1.441990326,"remaining_time":4.85491066},
{"learn":[0.2492245693],"iteration":229,"passed_time":1.44845257,"remaining_time":4.849167298},
{"learn":[0.2488660554],"iteration":230,"passed_time":1.454671613,"remaining_time":4.842608097},
{"learn":[0.2486203705],"iteration":231,"passed_time":1.460800035,"remaining_time":4.835751839},
{"learn":[0.2484541367],"iteration":232,"passed_time":1.466693464,"remaining_time":4.82812827},
{"learn":[0.248139423],"iteration":233,"passed_time":1.472779012,"remaining_time":4.821148389},
{"learn":[0.2479845128],"iteration":234,"passed_time":1.478580069,"remaining_time":4.813250012},
{"learn":[0.2478120937],"iteration":235,"passed_time":1.484317129,"remaining_time":4.80516223},
{"learn":[0.2475938584],"iteration":236,"passed_time":1.489646743,"remaining_time":4.795782554},
{"learn":[0.2473947464],"iteration":237,"passed_time":1.495572838,"remaining_time":4.78834665},
{"learn":[0.2472147449],"iteration":238,"passed_time":1.501363771,"remaining_time":4.780493011},
{"learn":[0.2470226815],"iteration":239,"passed_time":1.507149204,"remaining_time":4.772639146},
{"learn":[0.2468346112],"iteration":240,"passed_time":1.513815108,"remaining_time":4.76757538},
{"learn":[0.24666058],"iteration":241,"passed_time":1.520152814,"remaining_time":4.761470384},
{"learn":[0.2465617542],"iteration":242,"passed_time":1.525340891,"remaining_time":4.751782119},
{"learn":[0.2463701999],"iteration":243,"passed_time":1.531679848,"remaining_time":4.745696577},
{"learn":[0.2460909628],"iteration":244,"passed_time":1.537246163,"remaining_time":4.737227971},
{"learn":[0.2458314599],"iteration":245,"passed_time":1.542973431,"remaining_time":4.729276288},
{"learn":[0.2456358162],"iteration":246,"passed_time":1.549707916,"remaining_time":4.7244132},
{"learn":[0.2454594546],"iteration":247,"passed_time":1.555667009,"remaining_time":4.717183835},
{"learn":[0.2453236141],"iteration":248,"passed_time":1.561022623,"remaining_time":4.708144539},
{"learn":[0.2450831367],"iteration":249,"passed_time":1.566896387,"remaining_time":4.70068916},
{"learn":[0.244905423],"iteration":250,"passed_time":1.572215418,"remaining_time":4.691591029},
{"learn":[0.2446585205],"iteration":251,"passed_time":1.578359423,"remaining_time":4.684971619},
{"learn":[0.2444307245],"iteration":252,"passed_time":1.583692996,"remaining_time":4.675963113},
{"learn":[0.2442143663],"iteration":253,"passed_time":1.58914194,"remaining_time":4.667322389},
{"learn":[0.2437866906],"iteration":254,"passed_time":1.595419564,"remaining_time":4.661127747},
{"learn":[0.2435217582],"iteration":255,"passed_time":1.600856634,"remaining_time":4.652489592},
{"learn":[0.2433025319],"iteration":256,"passed_time":1.606629526,"remaining_time":4.644847228},
{"learn":[0.2430295887],"iteration":257,"passed_time":1.612574578,"remaining_time":4.637714484},
{"learn":[0.2429143579],"iteration":258,"passed_time":1.61935277,"remaining_time":4.632974527},
{"learn":[0.2427562061],"iteration":259,"passed_time":1.624928835,"remaining_time":4.624797452},
{"learn":[0.2425479736],"iteration":260,"passed_time":1.630827472,"remaining_time":4.617553647},
{"learn":[0.2424421245],"iteration":261,"passed_time":1.636114588,"remaining_time":4.60859758},
{"learn":[0.2422173455],"iteration":262,"passed_time":1.64159149,"remaining_time":4.600201247},
{"learn":[0.2420494856],"iteration":263,"passed_time":1.647620414,"remaining_time":4.593366004},
{"learn":[0.2419101342],"iteration":264,"passed_time":1.654847341,"remaining_time":4.589859606},
{"learn":[0.2416663238],"iteration":265,"passed_time":1.662164098,"remaining_time":4.586573113},
{"learn":[0.2414151382],"iteration":266,"passed_time":1.668922082,"remaining_time":4.58172242},
{"learn":[0.241231471],"iteration":267,"passed_time":1.676220298,"remaining_time":4.578333053},
{"learn":[0.2409348921],"iteration":268,"passed_time":1.683536222,"remaining_time":4.574962744},
{"learn":[0.2406545374],"iteration":269,"passed_time":1.690228583,"remaining_time":4.56987728},
{"learn":[0.2404701334],"iteration":270,"passed_time":1.695880312,"remaining_time":4.561980618},
{"learn":[0.2403206055],"iteration":271,"passed_time":1.701396962,"remaining_time":4.553738928},
{"learn":[0.2402060025],"iteration":272,"passed_time":1.707298891,"remaining_time":4.546543201},
{"learn":[0.2400216243],"iteration":273,"passed_time":1.712937662,"remaining_time":4.538659645},
{"learn":[0.2398133091],"iteration":274,"passed_time":1.719632898,"remaining_time":4.533577641},
{"learn":[0.2395350065],"iteration":275,"passed_time":1.725073134,"remaining_time":4.525191845},
{"learn":[0.2393111276],"iteration":276,"passed_time":1.730394166,"remaining_time":4.51651618},
{"learn":[0.2391020566],"iteration":277,"passed_time":1.735917774,"remaining_time":4.508390766},
{"learn":[0.2388955233],"iteration":278,"passed_time":1.742443599,"remaining_time":4.50287396},
{"learn":[0.2386681715],"iteration":279,"passed_time":1.748313154,"remaining_time":4.495662396},
{"learn":[0.2384874121],"iteration":280,"passed_time":1.754085671,"remaining_time":4.48821209},
{"learn":[0.2383507222],"iteration":281,"passed_time":1.761593921,"remaining_time":4.485193034},
{"learn":[0.2380737583],"iteration":282,"passed_time":1.768740309,"remaining_time":4.481225448},
{"learn":[0.2378801304],"iteration":283,"passed_time":1.775051266,"remaining_time":4.475129249},
{"learn":[0.2376646837],"iteration":284,"passed_time":1.780578333,"remaining_time":4.46706494},
{"learn":[0.23741225],"iteration":285,"passed_time":1.787062742,"remaining_time":4.461408385},
{"learn":[0.2371985147],"iteration":286,"passed_time":1.794247004,"remaining_time":4.457484717},
{"learn":[0.2369756404],"iteration":287,"passed_time":1.800394716,"remaining_time":4.450975827},
{"learn":[0.2368446641],"iteration":288,"passed_time":1.806999747,"remaining_time":4.445594533},
{"learn":[0.2366762505],"iteration":289,"passed_time":1.813306871,"remaining_time":4.439475443},
{"learn":[0.2365171015],"iteration":290,"passed_time":1.82102124,"remaining_time":4.436783708},
{"learn":[0.2363454965],"iteration":291,"passed_time":1.827059206,"remaining_time":4.429992869},
{"learn":[0.2361743278],"iteration":292,"passed_time":1.832365155,"remaining_time":4.421440834},
{"learn":[0.2361001511],"iteration":293,"passed_time":1.83784389,"remaining_time":4.413325803},
{"learn":[0.2358085946],"iteration":294,"passed_time":1.843583782,"remaining_time":4.405852768},
{"learn":[0.2357026377],"iteration":295,"passed_time":1.849094933,"remaining_time":4.397847407},
{"learn":[0.2354706847],"iteration":296,"passed_time":1.854477629,"remaining_time":4.389554792},
{"learn":[0.2352633451],"iteration":297,"passed_time":1.859481504,"remaining_time":4.380389316},
{"learn":[0.2351519495],"iteration":298,"passed_time":1.864697415,"remaining_time":4.371748788},
{"learn":[0.2348892488],"iteration":299,"passed_time":1.871011913,"remaining_time":4.365694464},
{"learn":[0.2346616528],"iteration":300,"passed_time":1.876831512,"remaining_time":4.358489125},
{"learn":[0.2344229969],"iteration":301,"passed_time":1.881826971,"remaining_time":4.349388164},
{"learn":[0.2342333262],"iteration":302,"passed_time":1.88712567,"remaining_time":4.341011854},
{"learn":[0.2341065301],"iteration":303,"passed_time":1.892933727,"remaining_time":4.333821954},
{"learn":[0.2339921491],"iteration":304,"passed_time":1.899244142,"remaining_time":4.327785833},
{"learn":[0.2338379269],"iteration":305,"passed_time":1.904914496,"remaining_time":4.320296275},
{"learn":[0.2334715334],"iteration":306,"passed_time":1.910579141,"remaining_time":4.312805683},
{"learn":[0.2333644825],"iteration":307,"passed_time":1.916016377,"remaining_time":4.304816016},
{"learn":[0.2331566137],"iteration":308,"passed_time":1.924144649,"remaining_time":4.302860687},
{"learn":[0.232990357],"iteration":309,"passed_time":1.928733788,"remaining_time":4.292988109},
{"learn":[0.2327347828],"iteration":310,"passed_time":1.933705498,"remaining_time":4.283997068},
{"learn":[0.232609451],"iteration":311,"passed_time":1.93926423,"remaining_time":4.276326251},
{"learn":[0.2322670439],"iteration":312,"passed_time":1.944870794,"remaining_time":4.268773915},
{"learn":[0.2320540752],"iteration":313,"passed_time":1.950045414,"remaining_time":4.260290299},
{"learn":[0.2319471963],"iteration":314,"passed_time":1.955133662,"remaining_time":4.251639867},
{"learn":[0.2317629092],"iteration":315,"passed_time":1.959786007,"remaining_time":4.242068446},
{"learn":[0.2316066142],"iteration":316,"passed_time":1.965777891,"remaining_time":4.235414195},
{"learn":[0.231383142],"iteration":317,"passed_time":1.97137758,"remaining_time":4.227922987},
{"learn":[0.2311741526],"iteration":318,"passed_time":1.976728111,"remaining_time":4.219911736},
{"learn":[0.2310673276],"iteration":319,"passed_time":1.981805693,"remaining_time":4.211337097},
{"learn":[0.2307643342],"iteration":320,"passed_time":1.988131066,"remaining_time":4.205423656},
{"learn":[0.230653026],"iteration":321,"passed_time":1.993497971,"remaining_time":4.197489516},
{"learn":[0.2304746347],"iteration":322,"passed_time":1.99860601,"remaining_time":4.189028695},
{"learn":[0.2302893025],"iteration":323,"passed_time":2.003863043,"remaining_time":4.180899436},
{"learn":[0.2301906224],"iteration":324,"passed_time":2.009341736,"remaining_time":4.173248222},
{"learn":[0.2300821729],"iteration":325,"passed_time":2.01459977,"remaining_time":4.165154126},
{"learn":[0.2298801451],"iteration":326,"passed_time":2.02058053,"remaining_time":4.158564822},
{"learn":[0.2296363568],"iteration":327,"passed_time":2.026993192,"remaining_time":4.152864101},
{"learn":[0.2294924689],"iteration":328,"passed_time":2.031960319,"remaining_time":4.144210863},
{"learn":[0.2292163515],"iteration":329,"passed_time":2.037644588,"remaining_time":4.137035982},
{"learn":[0.2290813617],"iteration":330,"passed_time":2.042373223,"remaining_time":4.127938629},
{"learn":[0.228860011],"iteration":331,"passed_time":2.047724629,"remaining_time":4.120120638},
{"learn":[0.2284968905],"iteration":332,"passed_time":2.053773594,"remaining_time":4.113714677},
{"learn":[0.2283352789],"iteration":333,"passed_time":2.058883883,"remaining_time":4.10543912},
{"learn":[0.2280344274],"iteration":334,"passed_time":2.064070169,"remaining_time":4.097333321},
{"learn":[0.2277813027],"iteration":335,"passed_time":2.06988181,"remaining_time":4.090480719},
{"learn":[0.2276117876],"iteration":336,"passed_time":2.075442458,"remaining_time":4.083140504},
{"learn":[0.2274767458],"iteration":337,"passed_time":2.080752032,"remaining_time":4.075319068},
{"learn":[0.2271923535],"iteration":338,"passed_time":2.085967817,"remaining_time":4.067329578},
{"learn":[0.2269122055],"iteration":339,"passed_time":2.091199102,"remaining_time":4.059386491},
{"learn":[0.2264697902],"iteration":340,"passed_time":2.096490593,"remaining_time":4.051575661},
{"learn":[0.2261434243],"iteration":341,"passed_time":2.102425396,"remaining_time":4.045017282},
{"learn":[0.2259299097],"iteration":342,"passed_time":2.107288609,"remaining_time":4.03640996},
{"learn":[0.2257075421],"iteration":343,"passed_time":2.112317734,"remaining_time":4.028140795},
{"learn":[0.2253464496],"iteration":344,"passed_time":2.117732846,"remaining_time":4.020623229},
{"learn":[0.2250450587],"iteration":345,"passed_time":2.123480613,"remaining_time":4.013746592},
{"learn":[0.2247984441],"iteration":346,"passed_time":2.129847318,"remaining_time":4.008041207},
{"learn":[0.2246100662],"iteration":347,"passed_time":2.135936658,"remaining_time":4.001812359},
{"learn":[0.2244860769],"iteration":348,"passed_time":2.1411879,"remaining_time":3.994020983},
{"learn":[0.224269675],"iteration":349,"passed_time":2.146019406,"remaining_time":3.985464612},
{"learn":[0.2241070117],"iteration":350,"passed_time":2.151420019,"remaining_time":3.977981744},
{"learn":[0.2238459422],"iteration":351,"passed_time":2.156975334,"remaining_time":3.970795502},
{"learn":[0.2237059609],"iteration":352,"passed_time":2.162383488,"remaining_time":3.963348773},
{"learn":[0.2235766547],"iteration":353,"passed_time":2.167392322,"remaining_time":3.955184858},
{"learn":[0.2233864062],"iteration":354,"passed_time":2.172659813,"remaining_time":3.947508675},
{"learn":[0.2232675887],"iteration":355,"passed_time":2.178801943,"remaining_time":3.941428234},
{"learn":[0.2231673795],"iteration":356,"passed_time":2.184717163,"remaining_time":3.934938756},
{"learn":[0.2230563283],"iteration":357,"passed_time":2.189681123,"remaining_time":3.926746595},
{"learn":[0.2228527934],"iteration":358,"passed_time":2.194769829,"remaining_time":3.918795155},
{"learn":[0.222633747],"iteration":359,"passed_time":2.200142067,"remaining_time":3.911363676},
{"learn":[0.2224731087],"iteration":360,"passed_time":2.20588146,"remaining_time":3.904593499},
{"learn":[0.2223075284],"iteration":361,"passed_time":2.21160327,"remaining_time":3.897798029},
{"learn":[0.2222196551],"iteration":362,"passed_time":2.216314739,"remaining_time":3.889235506},
{"learn":[0.2219998674],"iteration":363,"passed_time":2.221644062,"remaining_time":3.88177369},
{"learn":[0.2217159141],"iteration":364,"passed_time":2.22693222,"remaining_time":3.874251944},
{"learn":[0.2213657699],"iteration":365,"passed_time":2.233512709,"remaining_time":3.868981032},
{"learn":[0.2212123366],"iteration":366,"passed_time":2.239330683,"remaining_time":3.862387799},
{"learn":[0.2210548553],"iteration":367,"passed_time":2.254670757,"remaining_time":3.872151952},
{"learn":[0.2209023667],"iteration":368,"passed_time":2.268636293,"remaining_time":3.879429542},
{"learn":[0.2207364688],"iteration":369,"passed_time":2.282212301,"remaining_time":3.885929052},
{"learn":[0.2205793747],"iteration":370,"passed_time":2.289878129,"remaining_time":3.882300117},
{"learn":[0.2203371437],"iteration":371,"passed_time":2.296404163,"remaining_time":3.876725307},
{"learn":[0.2202129297],"iteration":372,"passed_time":2.303500052,"remaining_time":3.872103305},
{"learn":[0.2199192363],"iteration":373,"passed_time":2.309813009,"remaining_time":3.866157603},
{"learn":[0.2196887062],"iteration":374,"passed_time":2.315876641,"remaining_time":3.859794402},
{"learn":[0.2194668232],"iteration":375,"passed_time":2.331270338,"remaining_time":3.868916732},
{"learn":[0.2193282684],"iteration":376,"passed_time":2.342142227,"remaining_time":3.870436625},
{"learn":[0.2191294277],"iteration":377,"passed_time":2.352453843,"remaining_time":3.870969022},
{"learn":[0.2189864111],"iteration":378,"passed_time":2.368135947,"remaining_time":3.880243861},
{"learn":[0.2188048783],"iteration":379,"passed_time":2.374975012,"remaining_time":3.87495923},
{"learn":[0.2186782469],"iteration":380,"passed_time":2.388734638,"remaining_time":3.880910082},
{"learn":[0.2185739833],"iteration":381,"passed_time":2.394805395,"remaining_time":3.874318676},
{"learn":[0.2183754232],"iteration":382,"passed_time":2.40162646,"remaining_time":3.86893871},
{"learn":[0.21817296],"iteration":383,"passed_time":2.407752507,"remaining_time":3.862436313},
{"learn":[0.2179270672],"iteration":384,"passed_time":2.414165544,"remaining_time":3.856394311},
{"learn":[0.2178149056],"iteration":385,"passed_time":2.419707443,"remaining_time":3.84896469},
{"learn":[0.2176534798],"iteration":386,"passed_time":2.425458336,"remaining_time":3.841875865},
{"learn":[0.2175133221],"iteration":387,"passed_time":2.431496094,"remaining_time":3.835246416},
{"learn":[0.2173816372],"iteration":388,"passed_time":2.437130448,"remaining_time":3.827986385},
{"learn":[0.2170854633],"iteration":389,"passed_time":2.442884049,"remaining_time":3.820921204},
{"learn":[0.2169584261],"iteration":390,"passed_time":2.44900647,"remaining_time":3.814437188},
{"learn":[0.2168452878],"iteration":391,"passed_time":2.454158674,"remaining_time":3.806450189},
{"learn":[0.2166170565],"iteration":392,"passed_time":2.459921275,"remaining_time":3.799420391},
{"learn":[0.2163340484],"iteration":393,"passed_time":2.468108711,"remaining_time":3.796126596},
{"learn":[0.216230241],"iteration":394,"passed_time":2.473543531,"remaining_time":3.78859199},
{"learn":[0.2161058494],"iteration":395,"passed_time":2.479220467,"remaining_time":3.781437278},
{"learn":[0.2159364149],"iteration":396,"passed_time":2.485081606,"remaining_time":3.774569794},
{"learn":[0.2157869974],"iteration":397,"passed_time":2.492064374,"remaining_time":3.769403902},
{"learn":[0.2156583778],"iteration":398,"passed_time":2.498773026,"remaining_time":3.763816012},
{"learn":[0.2155355418],"iteration":399,"passed_time":2.504283302,"remaining_time":3.756424952},
{"learn":[0.2153720664],"iteration":400,"passed_time":2.509374549,"remaining_time":3.748417344},
{"learn":[0.2151911984],"iteration":401,"passed_time":2.515480096,"remaining_time":3.741933079},
{"learn":[0.2150156576],"iteration":402,"passed_time":2.520933665,"remaining_time":3.734484859},
{"learn":[0.2148019043],"iteration":403,"passed_time":2.526585144,"remaining_time":3.72733848},
{"learn":[0.21465352],"iteration":404,"passed_time":2.532473407,"remaining_time":3.720547351},
{"learn":[0.2144348387],"iteration":405,"passed_time":2.53800989,"remaining_time":3.713245997},
{"learn":[0.214230251],"iteration":406,"passed_time":2.54383928,"remaining_time":3.706380081},
{"learn":[0.2140707465],"iteration":407,"passed_time":2.549667503,"remaining_time":3.699517553},
{"learn":[0.2139395895],"iteration":408,"passed_time":2.554908204,"remaining_time":3.691811121},
{"learn":[0.213748509],"iteration":409,"passed_time":2.560712428,"remaining_time":3.68492764},
{"learn":[0.2136254518],"iteration":410,"passed_time":2.567069883,"remaining_time":3.678842242},
{"learn":[0.2133782199],"iteration":411,"passed_time":2.572277252,"remaining_time":3.671114136},
{"learn":[0.2132039613],"iteration":412,"passed_time":2.579200689,"remaining_time":3.665837299},
{"learn":[0.2130401198],"iteration":413,"passed_time":2.58459201,"remaining_time":3.658383859},
{"learn":[0.2129244331],"iteration":414,"passed_time":2.590169741,"remaining_time":3.651203129},
{"learn":[0.2127610219],"iteration":415,"passed_time":2.596460949,"remaining_time":3.645031717},
{"learn":[0.2126488311],"iteration":416,"passed_time":2.601866686,"remaining_time":3.63762177},
{"learn":[0.2125255812],"iteration":417,"passed_time":2.607327422,"remaining_time":3.630297989},
{"learn":[0.2123944176],"iteration":418,"passed_time":2.613588505,"remaining_time":3.624092892},
{"learn":[0.2123030275],"iteration":419,"passed_time":2.618537383,"remaining_time":3.616075433},
{"learn":[0.2121020708],"iteration":420,"passed_time":2.624039075,"remaining_time":3.608832837},
{"learn":[0.2118276391],"iteration":421,"passed_time":2.630234411,"remaining_time":3.602548553},
{"learn":[0.2116918965],"iteration":422,"passed_time":2.635769227,"remaining_time":3.595363698},
{"learn":[0.2115643734],"iteration":423,"passed_time":2.640867933,"remaining_time":3.587594173},
{"learn":[0.2110787277],"iteration":424,"passed_time":2.64743809,"remaining_time":3.581828004},
{"learn":[0.2108597181],"iteration":425,"passed_time":2.652667041,"remaining_time":3.574250896},
{"learn":[0.2106618653],"iteration":426,"passed_time":2.658445349,"remaining_time":3.567421979},
{"learn":[0.2103952805],"iteration":427,"passed_time":2.664600978,"remaining_time":3.561102242},
{"learn":[0.2102263116],"iteration":428,"passed_time":2.671564497,"remaining_time":3.555858573},
{"learn":[0.2100203293],"iteration":429,"passed_time":2.677605255,"remaining_time":3.54938371},
{"learn":[0.2099067046],"iteration":430,"passed_time":2.68331744,"remaining_time":3.542477084},
{"learn":[0.2097817686],"iteration":431,"passed_time":2.688800425,"remaining_time":3.535274632},
{"learn":[0.209643484],"iteration":432,"passed_time":2.694177538,"remaining_time":3.527941487},
{"learn":[0.2095746353],"iteration":433,"passed_time":2.699675063,"remaining_time":3.520774391},
{"learn":[0.2094924987],"iteration":434,"passed_time":2.705753195,"remaining_time":3.514369092},
{"learn":[0.2093686161],"iteration":435,"passed_time":2.713663974,"remaining_time":3.510335966},
{"learn":[0.2092850204],"iteration":436,"passed_time":2.719668108,"remaining_time":3.503828706},
{"learn":[0.2091460221],"iteration":437,"passed_time":2.725556996,"remaining_time":3.497175871},
{"learn":[0.2089786373],"iteration":438,"passed_time":2.730920609,"remaining_time":3.489855266},
{"learn":[0.2087765373],"iteration":439,"passed_time":2.736567547,"remaining_time":3.48290415},
{"learn":[0.2086427449],"iteration":440,"passed_time":2.742442435,"remaining_time":3.476247894},
{"learn":[0.2084317173],"iteration":441,"passed_time":2.748158995,"remaining_time":3.469395292},
{"learn":[0.2082363623],"iteration":442,"passed_time":2.753212244,"remaining_time":3.461713815},
{"learn":[0.2081230359],"iteration":443,"passed_time":2.757926087,"remaining_time":3.453619155},
{"learn":[0.2079796925],"iteration":444,"passed_time":2.763424988,"remaining_time":3.446518806},
{"learn":[0.2078517223],"iteration":445,"passed_time":2.768737103,"remaining_time":3.439193622},
{"learn":[0.2077301821],"iteration":446,"passed_time":2.775196556,"remaining_time":3.433296857},
{"learn":[0.2075987574],"iteration":447,"passed_time":2.780404091,"remaining_time":3.425855041},
{"learn":[0.2074569541],"iteration":448,"passed_time":2.786212815,"remaining_time":3.419160938},
{"learn":[0.2073241426],"iteration":449,"passed_time":2.793249873,"remaining_time":3.413972067},
{"learn":[0.2072292262],"iteration":450,"passed_time":2.798951559,"remaining_time":3.407149458},
{"learn":[0.2071098906],"iteration":451,"passed_time":2.803775607,"remaining_time":3.399267771},
{"learn":[0.2069955869],"iteration":452,"passed_time":2.809166344,"remaining_time":3.392083864},
{"learn":[0.2068967712],"iteration":453,"passed_time":2.814839281,"remaining_time":3.385247241},
{"learn":[0.2067632246],"iteration":454,"passed_time":2.820305141,"remaining_time":3.378167696},
{"learn":[0.2066408791],"iteration":455,"passed_time":2.830420472,"remaining_time":3.376641966},
{"learn":[0.2065388171],"iteration":456,"passed_time":2.835900748,"remaining_time":3.369571349},
{"learn":[0.2064564616],"iteration":457,"passed_time":2.842387158,"remaining_time":3.36369834},
{"learn":[0.2063298787],"iteration":458,"passed_time":2.848301128,"remaining_time":3.357147953},
{"learn":[0.2061274049],"iteration":459,"passed_time":2.853810737,"remaining_time":3.350125648},
{"learn":[0.2060113725],"iteration":460,"passed_time":2.860494098,"remaining_time":3.344482254},
{"learn":[0.2058992064],"iteration":461,"passed_time":2.866415652,"remaining_time":3.337947231},
{"learn":[0.2056146833],"iteration":462,"passed_time":2.87367841,"remaining_time":3.332970424},
{"learn":[0.2053660419],"iteration":463,"passed_time":2.880364897,"remaining_time":3.32731807},
{"learn":[0.2052541439],"iteration":464,"passed_time":2.885939545,"remaining_time":3.320382057},
{"learn":[0.2051507533],"iteration":465,"passed_time":2.891607523,"remaining_time":3.313558836},
{"learn":[0.2050691538],"iteration":466,"passed_time":2.896680022,"remaining_time":3.306060924},
{"learn":[0.2049713956],"iteration":467,"passed_time":2.902494454,"remaining_time":3.299416772},
{"learn":[0.2048663891],"iteration":468,"passed_time":2.908372592,"remaining_time":3.292848286},
{"learn":[0.2047150308],"iteration":469,"passed_time":2.913696332,"remaining_time":3.285657565},
{"learn":[0.204479104],"iteration":470,"passed_time":2.919667008,"remaining_time":3.279201375},
{"learn":[0.2043540656],"iteration":471,"passed_time":2.926171792,"remaining_time":3.273344717},
{"learn":[0.2042293337],"iteration":472,"passed_time":2.931771065,"remaining_time":3.266476429},
{"learn":[0.2041202956],"iteration":473,"passed_time":2.937980234,"remaining_time":3.260290301},
{"learn":[0.203930412],"iteration":474,"passed_time":2.942945777,"remaining_time":3.252729543},
{"learn":[0.2038348389],"iteration":475,"passed_time":2.947665079,"remaining_time":3.244908616},
{"learn":[0.2036494444],"iteration":476,"passed_time":2.953215644,"remaining_time":3.238012122},
{"learn":[0.2034439118],"iteration":477,"passed_time":2.958860624,"remaining_time":3.231224363},
{"learn":[0.2031726151],"iteration":478,"passed_time":2.964515311,"remaining_time":3.224451935},
{"learn":[0.2030558585],"iteration":479,"passed_time":2.970529361,"remaining_time":3.218073475},
{"learn":[0.2029344088],"iteration":480,"passed_time":2.976857234,"remaining_time":3.212035145},
{"learn":[0.2028203913],"iteration":481,"passed_time":2.98154537,"remaining_time":3.204233406},
{"learn":[0.2026839843],"iteration":482,"passed_time":2.987265347,"remaining_time":3.197549036},
{"learn":[0.2024706391],"iteration":483,"passed_time":2.992619211,"remaining_time":3.190478332},
{"learn":[0.2023404355],"iteration":484,"passed_time":2.99803224,"remaining_time":3.183477533},
{"learn":[0.2021787935],"iteration":485,"passed_time":3.004181994,"remaining_time":3.177262438},
{"learn":[0.2020653436],"iteration":486,"passed_time":3.009227034,"remaining_time":3.169883919},
{"learn":[0.2018843983],"iteration":487,"passed_time":3.014604939,"remaining_time":3.162864199},
{"learn":[0.2017770894],"iteration":488,"passed_time":3.020228586,"remaining_time":3.156107991},
{"learn":[0.201585565],"iteration":489,"passed_time":3.02488164,"remaining_time":3.148346196},
{"learn":[0.2014078751],"iteration":490,"passed_time":3.029868516,"remaining_time":3.140943125},
{"learn":[0.2012725098],"iteration":491,"passed_time":3.034890891,"remaining_time":3.133586529},
{"learn":[0.201164158],"iteration":492,"passed_time":3.040744363,"remaining_time":3.127094101},
{"learn":[0.2009894615],"iteration":493,"passed_time":3.046199557,"remaining_time":3.120196307},
{"learn":[0.2008837249],"iteration":494,"passed_time":3.051212182,"remaining_time":3.112852832},
{"learn":[0.2004915283],"iteration":495,"passed_time":3.056275722,"remaining_time":3.105570492},
{"learn":[0.2003942709],"iteration":496,"passed_time":3.061205017,"remaining_time":3.098161214},
{"learn":[0.2002555333],"iteration":497,"passed_time":3.067286315,"remaining_time":3.091923153},
{"learn":[0.2001566641],"iteration":498,"passed_time":3.072559931,"remaining_time":3.084874801},
{"learn":[0.2000742048],"iteration":499,"passed_time":3.078398738,"remaining_time":3.078398738},
{"learn":[0.200005124],"iteration":500,"passed_time":3.083127289,"remaining_time":3.070819396},
{"learn":[0.1998692892],"iteration":501,"passed_time":3.088822058,"remaining_time":3.06420993},
{"learn":[0.1997420581],"iteration":502,"passed_time":3.093556401,"remaining_time":3.056655132},
{"learn":[0.1995850521],"iteration":503,"passed_time":3.098983929,"remaining_time":3.049793708},
{"learn":[0.1994786922],"iteration":504,"passed_time":3.104465955,"remaining_time":3.042991382},
{"learn":[0.1992465772],"iteration":505,"passed_time":3.110256763,"remaining_time":3.036495733},
{"learn":[0.199163533],"iteration":506,"passed_time":3.115260347,"remaining_time":3.029237379},
{"learn":[0.1990582139],"iteration":507,"passed_time":3.120643751,"remaining_time":3.022355759},
{"learn":[0.1989521574],"iteration":508,"passed_time":3.125988574,"remaining_time":3.015442809},
{"learn":[0.1988313431],"iteration":509,"passed_time":3.131120904,"remaining_time":3.008331849},
{"learn":[0.1987106754],"iteration":510,"passed_time":3.136027324,"remaining_time":3.001012449},
{"learn":[0.1985500774],"iteration":511,"passed_time":3.140718252,"remaining_time":2.993497083},
{"learn":[0.1983683237],"iteration":512,"passed_time":3.146173779,"remaining_time":2.986718577},
{"learn":[0.1982198108],"iteration":513,"passed_time":3.151587141,"remaining_time":2.979905351},
{"learn":[0.198063481],"iteration":514,"passed_time":3.156361565,"remaining_time":2.972495843},
{"learn":[0.1978712435],"iteration":515,"passed_time":3.161343692,"remaining_time":2.96529137},
{"learn":[0.1977864331],"iteration":516,"passed_time":3.166338651,"remaining_time":2.958107482},
{"learn":[0.197650041],"iteration":517,"passed_time":3.171937715,"remaining_time":2.951494167},
{"learn":[0.1975395244],"iteration":518,"passed_time":3.177061836,"remaining_time":2.944444592},
{"learn":[0.1974228514],"iteration":519,"passed_time":3.182445991,"remaining_time":2.937642453},
{"learn":[0.197325205],"iteration":520,"passed_time":3.18763636,"remaining_time":2.930667594},
{"learn":[0.1972265536],"iteration":521,"passed_time":3.193056472,"remaining_time":2.923909949},
{"learn":[0.1971339949],"iteration":522,"passed_time":3.198467209,"remaining_time":2.917148869},
{"learn":[0.1970272226],"iteration":523,"passed_time":3.20380574,"remaining_time":2.910327352},
{"learn":[0.1968882721],"iteration":524,"passed_time":3.20851725,"remaining_time":2.902944179},
{"learn":[0.1967295681],"iteration":525,"passed_time":3.213481002,"remaining_time":2.89579847},
{"learn":[0.1965962623],"iteration":526,"passed_time":3.218333508,"remaining_time":2.888561194},
{"learn":[0.1964742648],"iteration":527,"passed_time":3.222900106,"remaining_time":2.881077367},
{"learn":[0.1963385333],"iteration":528,"passed_time":3.228060976,"remaining_time":2.874133686},
{"learn":[0.1961903959],"iteration":529,"passed_time":3.233538669,"remaining_time":2.867477688},
{"learn":[0.1960650642],"iteration":530,"passed_time":3.23960351,"remaining_time":2.861344719},
{"learn":[0.1959544217],"iteration":531,"passed_time":3.244239981,"remaining_time":2.853955472},
{"learn":[0.195870554],"iteration":532,"passed_time":3.24898074,"remaining_time":2.846667928},
{"learn":[0.1957325467],"iteration":533,"passed_time":3.253863119,"remaining_time":2.839513509},
{"learn":[0.1955941028],"iteration":534,"passed_time":3.258626503,"remaining_time":2.832264157},
{"learn":[0.1955049999],"iteration":535,"passed_time":3.263542756,"remaining_time":2.825156416},
{"learn":[0.1953675121],"iteration":536,"passed_time":3.269175194,"remaining_time":2.81867433},
{"learn":[0.1952431873],"iteration":537,"passed_time":3.274163487,"remaining_time":2.811642251},
{"learn":[0.1951416918],"iteration":538,"passed_time":3.278852998,"remaining_time":2.804362212},
{"learn":[0.1948560826],"iteration":539,"passed_time":3.28401141,"remaining_time":2.797491201},
{"learn":[0.1947400485],"iteration":540,"passed_time":3.289123657,"remaining_time":2.790587354},
{"learn":[0.1946414377],"iteration":541,"passed_time":3.294688764,"remaining_time":2.784072793},
{"learn":[0.1945270937],"iteration":542,"passed_time":3.299547102,"remaining_time":2.776966898},
{"learn":[0.1943961962],"iteration":543,"passed_time":3.307552087,"remaining_time":2.772506896},
{"learn":[0.1942914119],"iteration":544,"passed_time":3.342905996,"remaining_time":2.790866474},
{"learn":[0.1941613129],"iteration":545,"passed_time":3.354497903,"remaining_time":2.78927115},
{"learn":[0.1939830832],"iteration":546,"passed_time":3.365605076,"remaining_time":2.787237841},
{"learn":[0.1938223523],"iteration":547,"passed_time":3.372803503,"remaining_time":2.781947415},
{"learn":[0.1936708509],"iteration":548,"passed_time":3.380000098,"remaining_time":2.776648532},
{"learn":[0.1935166668],"iteration":549,"passed_time":3.388781306,"remaining_time":2.77263925},
{"learn":[0.193432483],"iteration":550,"passed_time":3.395626329,"remaining_time":2.767034885},
{"learn":[0.1932855244],"iteration":551,"passed_time":3.40442562,"remaining_time":2.763012097},
{"learn":[0.193224756],"iteration":552,"passed_time":3.410178096,"remaining_time":2.756509238},
{"learn":[0.1931208544],"iteration":553,"passed_time":3.416528593,"remaining_time":2.750490528},
{"learn":[0.1930019035],"iteration":554,"passed_time":3.421807168,"remaining_time":2.743611153},
{"learn":[0.1928793789],"iteration":555,"passed_time":3.427558852,"remaining_time":2.737115342},
{"learn":[0.1927510404],"iteration":556,"passed_time":3.433448781,"remaining_time":2.730732155},
{"learn":[0.1926958063],"iteration":557,"passed_time":3.438406117,"remaining_time":2.723612013},
{"learn":[0.1926184311],"iteration":558,"passed_time":3.443726648,"remaining_time":2.716786139},
{"learn":[0.1925351344],"iteration":559,"passed_time":3.450625752,"remaining_time":2.711205948},
{"learn":[0.1923512439],"iteration":560,"passed_time":3.456073238,"remaining_time":2.704485119},
{"learn":[0.1922084918],"iteration":561,"passed_time":3.462242783,"remaining_time":2.698331564},
{"learn":[0.192047046],"iteration":562,"passed_time":3.467797641,"remaining_time":2.691700833},
{"learn":[0.1919077073],"iteration":563,"passed_time":3.473114756,"remaining_time":2.68489013},
{"learn":[0.1917533019],"iteration":564,"passed_time":3.478784859,"remaining_time":2.678356484},
{"learn":[0.1915701489],"iteration":565,"passed_time":3.485393848,"remaining_time":2.672545813},
{"learn":[0.1914153876],"iteration":566,"passed_time":3.491068035,"remaining_time":2.666018446},
{"learn":[0.1913114279],"iteration":567,"passed_time":3.497224288,"remaining_time":2.659860726},
{"learn":[0.1912164412],"iteration":568,"passed_time":3.502678191,"remaining_time":2.653171002},
{"learn":[0.1911380639],"iteration":569,"passed_time":3.508225173,"remaining_time":2.646555832},
{"learn":[0.1909658012],"iteration":570,"passed_time":3.514322887,"remaining_time":2.640358176},
{"learn":[0.1908777531],"iteration":571,"passed_time":3.519767123,"remaining_time":2.633671903},
{"learn":[0.1907240658],"iteration":572,"passed_time":3.525395686,"remaining_time":2.627127326},
{"learn":[0.1904543834],"iteration":573,"passed_time":3.5317716,"remaining_time":2.621140595},
{"learn":[0.1903256089],"iteration":574,"passed_time":3.536900429,"remaining_time":2.614230752},
{"learn":[0.1901519628],"iteration":575,"passed_time":3.541944428,"remaining_time":2.607264649},
{"learn":[0.1900727675],"iteration":576,"passed_time":3.547219587,"remaining_time":2.600474671},
{"learn":[0.1899380069],"iteration":577,"passed_time":3.552122174,"remaining_time":2.593417919},
{"learn":[0.1898343689],"iteration":578,"passed_time":3.557374833,"remaining_time":2.586623151},
{"learn":[0.1897484656],"iteration":579,"passed_time":3.563421132,"remaining_time":2.580408406},
{"learn":[0.1896634703],"iteration":580,"passed_time":3.568729039,"remaining_time":2.573661734},
{"learn":[0.189580736],"iteration":581,"passed_time":3.573884868,"remaining_time":2.566810781},
{"learn":[0.1894610462],"iteration":582,"passed_time":3.579332687,"remaining_time":2.560174495},
{"learn":[0.1893445497],"iteration":583,"passed_time":3.584329854,"remaining_time":2.553221266},
{"learn":[0.189265151],"iteration":584,"passed_time":3.590650686,"remaining_time":2.547213735},
{"learn":[0.189139594],"iteration":585,"passed_time":3.596631779,"remaining_time":2.540965114},
{"learn":[0.189070307],"iteration":586,"passed_time":3.601378622,"remaining_time":2.533849013},
{"learn":[0.1889508467],"iteration":587,"passed_time":3.606185004,"remaining_time":2.52678269},
{"learn":[0.188820433],"iteration":588,"passed_time":3.611355582,"remaining_time":2.519978173},
{"learn":[0.1886721962],"iteration":589,"passed_time":3.616268169,"remaining_time":2.512999914},
{"learn":[0.1886233081],"iteration":590,"passed_time":3.621380041,"remaining_time":2.50616656},
{"learn":[0.1884556916],"iteration":591,"passed_time":3.627510046,"remaining_time":2.500040707},
{"learn":[0.1883361006],"iteration":592,"passed_time":3.633092235,"remaining_time":2.493538853},
{"learn":[0.1881922198],"iteration":593,"passed_time":3.638068237,"remaining_time":2.486625764},
{"learn":[0.1881057169],"iteration":594,"passed_time":3.643347436,"remaining_time":2.479925566},
{"learn":[0.1879706145],"iteration":595,"passed_time":3.648327771,"remaining_time":2.473027549},
{"learn":[0.1876393437],"iteration":596,"passed_time":3.653899003,"remaining_time":2.466534838},
{"learn":[0.1875401531],"iteration":597,"passed_time":3.659719976,"remaining_time":2.460213094},
{"learn":[0.187426248],"iteration":598,"passed_time":3.664777891,"remaining_time":2.453382194},
{"learn":[0.1873340336],"iteration":599,"passed_time":3.669589273,"remaining_time":2.446392849},
{"learn":[0.1872491936],"iteration":600,"passed_time":3.675531618,"remaining_time":2.44016159},
{"learn":[0.1871513764],"iteration":601,"passed_time":3.680779277,"remaining_time":2.433472013},
{"learn":[0.1870338506],"iteration":602,"passed_time":3.685517369,"remaining_time":2.426451734},
{"learn":[0.1869381737],"iteration":603,"passed_time":3.691121225,"remaining_time":2.420006631},
{"learn":[0.1868009485],"iteration":604,"passed_time":3.696613793,"remaining_time":2.41349165},
{"learn":[0.1866912516],"iteration":605,"passed_time":3.701798245,"remaining_time":2.406779717},
{"learn":[0.1865956771],"iteration":606,"passed_time":3.706897326,"remaining_time":2.400017544},
{"learn":[0.1864632179],"iteration":607,"passed_time":3.712802088,"remaining_time":2.393780294},
{"learn":[0.1863125708],"iteration":608,"passed_time":3.71791521,"remaining_time":2.387035874},
{"learn":[0.1861795923],"iteration":609,"passed_time":3.722991,"remaining_time":2.380272934},
{"learn":[0.1860678303],"iteration":610,"passed_time":3.728037874,"remaining_time":2.373497108},
{"learn":[0.1859829511],"iteration":611,"passed_time":3.733413196,"remaining_time":2.366935163},
{"learn":[0.1858721685],"iteration":612,"passed_time":3.738864223,"remaining_time":2.360424885},
{"learn":[0.1857808129],"iteration":613,"passed_time":3.744111757,"remaining_time":2.353790127},
{"learn":[0.1856778141],"iteration":614,"passed_time":3.748994512,"remaining_time":2.346931523},
{"learn":[0.1854914668],"iteration":615,"passed_time":3.754419665,"remaining_time":2.340417453},
{"learn":[0.1853646799],"iteration":616,"passed_time":3.759809444,"remaining_time":2.333884955},
{"learn":[0.185265205],"iteration":617,"passed_time":3.764998105,"remaining_time":2.327231838},
{"learn":[0.1851450097],"iteration":618,"passed_time":3.769617952,"remaining_time":2.320233343},
{"learn":[0.1850588428],"iteration":619,"passed_time":3.774271506,"remaining_time":2.313263181},
{"learn":[0.1849659178],"iteration":620,"passed_time":3.780678501,"remaining_time":2.307370615},
{"learn":[0.1847862587],"iteration":621,"passed_time":3.786455809,"remaining_time":2.301093723},
{"learn":[0.1847072571],"iteration":622,"passed_time":3.791608555,"remaining_time":2.29444049},
{"learn":[0.1845578343],"iteration":623,"passed_time":3.796467852,"remaining_time":2.287615244},
{"learn":[0.1844242997],"iteration":624,"passed_time":3.801435645,"remaining_time":2.280861387},
{"learn":[0.1843343236],"iteration":625,"passed_time":3.806910297,"remaining_time":2.274416056},
{"learn":[0.184258316],"iteration":626,"passed_time":3.812395615,"remaining_time":2.267980166},
{"learn":[0.1841608798],"iteration":627,"passed_time":3.817251912,"remaining_time":2.261174699},
{"learn":[0.1840073798],"iteration":628,"passed_time":3.82222083,"remaining_time":2.254441857},
{"learn":[0.1838621354],"iteration":629,"passed_time":3.827199706,"remaining_time":2.247720462},
{"learn":[0.1837759398],"iteration":630,"passed_time":3.831857343,"remaining_time":2.240816735},
{"learn":[0.1837213358],"iteration":631,"passed_time":3.836783888,"remaining_time":2.234076694},
{"learn":[0.183627895],"iteration":632,"passed_time":3.842126419,"remaining_time":2.227583564},
{"learn":[0.1835266584],"iteration":633,"passed_time":3.847251916,"remaining_time":2.220968771},
{"learn":[0.1834322867],"iteration":634,"passed_time":3.852052214,"remaining_time":2.214171745},
{"learn":[0.1833620476],"iteration":635,"passed_time":3.856725601,"remaining_time":2.207308363},
{"learn":[0.1832581989],"iteration":636,"passed_time":3.862108839,"remaining_time":2.200856371},
{"learn":[0.1831850598],"iteration":637,"passed_time":3.867557616,"remaining_time":2.194444917},
{"learn":[0.1830837446],"iteration":638,"passed_time":3.872574075,"remaining_time":2.187792239},
{"learn":[0.1828948895],"iteration":639,"passed_time":3.877396123,"remaining_time":2.181035319},
{"learn":[0.1828083647],"iteration":640,"passed_time":3.8818636,"remaining_time":2.174085854},
{"learn":[0.1827011657],"iteration":641,"passed_time":3.886999596,"remaining_time":2.167516908},
{"learn":[0.1826102871],"iteration":642,"passed_time":3.891614567,"remaining_time":2.160663142},
{"learn":[0.1825519102],"iteration":643,"passed_time":3.897084719,"remaining_time":2.154289068},
{"learn":[0.1824425324],"iteration":644,"passed_time":3.9024335,"remaining_time":2.147850996},
{"learn":[0.1823585915],"iteration":645,"passed_time":3.908279972,"remaining_time":2.141689025},
{"learn":[0.1822604584],"iteration":646,"passed_time":3.913788414,"remaining_time":2.135343602},
{"learn":[0.1821597363],"iteration":647,"passed_time":3.919271107,"remaining_time":2.128986774},
{"learn":[0.182043989],"iteration":648,"passed_time":3.924340731,"remaining_time":2.12240924},
{"learn":[0.1819567995],"iteration":649,"passed_time":3.929117614,"remaining_time":2.115678715},
{"learn":[0.1818391087],"iteration":650,"passed_time":3.934093157,"remaining_time":2.109060694},
{"learn":[0.181766012],"iteration":651,"passed_time":3.939020285,"remaining_time":2.10242187},
{"learn":[0.1816917537],"iteration":652,"passed_time":3.944340067,"remaining_time":2.095996942},
{"learn":[0.1815713746],"iteration":653,"passed_time":3.950055502,"remaining_time":2.089784715},
{"learn":[0.1814252993],"iteration":654,"passed_time":3.955251329,"remaining_time":2.083300318},
{"learn":[0.1813558135],"iteration":655,"passed_time":3.960376617,"remaining_time":2.07678286},
{"learn":[0.1812839721],"iteration":656,"passed_time":3.965187999,"remaining_time":2.070105759},
{"learn":[0.1811570608],"iteration":657,"passed_time":3.970520614,"remaining_time":2.063705243},
{"learn":[0.1810789428],"iteration":658,"passed_time":3.975893394,"remaining_time":2.057328752},
{"learn":[0.1810086344],"iteration":659,"passed_time":3.981283465,"remaining_time":2.050964209},
{"learn":[0.1809200812],"iteration":660,"passed_time":3.986684411,"remaining_time":2.044608192},
{"learn":[0.1807912533],"iteration":661,"passed_time":3.99166587,"remaining_time":2.038040882},
{"learn":[0.1806860867],"iteration":662,"passed_time":3.997127855,"remaining_time":2.031722605},
{"learn":[0.1806108406],"iteration":663,"passed_time":4.001916321,"remaining_time":2.02506609},
{"learn":[0.1804990018],"iteration":664,"passed_time":4.007143689,"remaining_time":2.018636295},
{"learn":[0.1802482281],"iteration":665,"passed_time":4.012612258,"remaining_time":2.012331072},
{"learn":[0.1801610968],"iteration":666,"passed_time":4.017805669,"remaining_time":2.005890986},
{"learn":[0.1800340977],"iteration":667,"passed_time":4.022470806,"remaining_time":1.999192077},
{"learn":[0.1799092745],"iteration":668,"passed_time":4.027126568,"remaining_time":1.99249461},
{"learn":[0.1798456047],"iteration":669,"passed_time":4.032616385,"remaining_time":1.986214041},
{"learn":[0.1797236181],"iteration":670,"passed_time":4.038068621,"remaining_time":1.979917401},
{"learn":[0.179603947],"iteration":671,"passed_time":4.042900211,"remaining_time":1.973320341},
{"learn":[0.1794556548],"iteration":672,"passed_time":4.047577972,"remaining_time":1.966653784},
{"learn":[0.179346241],"iteration":673,"passed_time":4.052428727,"remaining_time":1.960076803},
{"learn":[0.1792593835],"iteration":674,"passed_time":4.057413854,"remaining_time":1.953569633},
{"learn":[0.1790814763],"iteration":675,"passed_time":4.062362273,"remaining_time":1.947049373},
{"learn":[0.1790079022],"iteration":676,"passed_time":4.067388356,"remaining_time":1.940570811},
{"learn":[0.1789234366],"iteration":677,"passed_time":4.073224912,"remaining_time":1.934481448},
{"learn":[0.1788452464],"iteration":678,"passed_time":4.079097009,"remaining_time":1.928409631},
{"learn":[0.178781508],"iteration":679,"passed_time":4.086217522,"remaining_time":1.922925893},
{"learn":[0.1787091867],"iteration":680,"passed_time":4.092611935,"remaining_time":1.917097221},
{"learn":[0.1786026009],"iteration":681,"passed_time":4.100136185,"remaining_time":1.911793705},
{"learn":[0.1785161919],"iteration":682,"passed_time":4.106383727,"remaining_time":1.90589113},
{"learn":[0.1783558584],"iteration":683,"passed_time":4.112482358,"remaining_time":1.89991875},
{"learn":[0.1782375127],"iteration":684,"passed_time":4.118818148,"remaining_time":1.894055061},
{"learn":[0.1781442764],"iteration":685,"passed_time":4.125506426,"remaining_time":1.888351338},
{"learn":[0.178052568],"iteration":686,"passed_time":4.130753252,"remaining_time":1.881988017},
{"learn":[0.1779830775],"iteration":687,"passed_time":4.136004994,"remaining_time":1.875630172},
{"learn":[0.177866098],"iteration":688,"passed_time":4.141794677,"remaining_time":1.869518352},
{"learn":[0.1777588829],"iteration":689,"passed_time":4.147052627,"remaining_time":1.863168572},
{"learn":[0.1776549432],"iteration":690,"passed_time":4.151954214,"remaining_time":1.856662594},
{"learn":[0.1775849772],"iteration":691,"passed_time":4.15685976,"remaining_time":1.850163014},
{"learn":[0.1774272638],"iteration":692,"passed_time":4.162210165,"remaining_time":1.843865109},
{"learn":[0.1773508432],"iteration":693,"passed_time":4.168029055,"remaining_time":1.8377765},
{"learn":[0.1772849565],"iteration":694,"passed_time":4.1729661,"remaining_time":1.83130167},
{"learn":[0.1771879875],"iteration":695,"passed_time":4.177763774,"remaining_time":1.824770384},
{"learn":[0.177116372],"iteration":696,"passed_time":4.182791065,"remaining_time":1.818343892},
{"learn":[0.1770501504],"iteration":697,"passed_time":4.188384588,"remaining_time":1.812166398},
{"learn":[0.1769863946],"iteration":698,"passed_time":4.193557624,"remaining_time":1.805809506},
{"learn":[0.1768574728],"iteration":699,"passed_time":4.198396547,"remaining_time":1.799312806},
{"learn":[0.1767567925],"iteration":700,"passed_time":4.204086941,"remaining_time":1.793184016},
{"learn":[0.176650241],"iteration":701,"passed_time":4.209005695,"remaining_time":1.786728913},
{"learn":[0.1765696258],"iteration":702,"passed_time":4.214139983,"remaining_time":1.780369239},
{"learn":[0.1764459416],"iteration":703,"passed_time":4.219578385,"remaining_time":1.774140912},
{"learn":[0.1763386811],"iteration":704,"passed_time":4.22496704,"remaining_time":1.76789401},
{"learn":[0.1762589614],"iteration":705,"passed_time":4.230301654,"remaining_time":1.761627035},
{"learn":[0.1761296887],"iteration":706,"passed_time":4.235155702,"remaining_time":1.755163537},
{"learn":[0.1760519162],"iteration":707,"passed_time":4.239958417,"remaining_time":1.748683415},
{"learn":[0.1759792796],"iteration":708,"passed_time":4.245441027,"remaining_time":1.742487079},
{"learn":[0.1757790928],"iteration":709,"passed_time":4.250881721,"remaining_time":1.736275633},
{"learn":[0.1757166055],"iteration":710,"passed_time":4.256007384,"remaining_time":1.729938304},
{"learn":[0.1755511365],"iteration":711,"passed_time":4.260916221,"remaining_time":1.723516674},
{"learn":[0.1754727089],"iteration":712,"passed_time":4.2665647,"remaining_time":1.717397011},
{"learn":[0.1753210918],"iteration":713,"passed_time":4.271582409,"remaining_time":1.711026007},
{"learn":[0.1752427019],"iteration":714,"passed_time":4.276237004,"remaining_time":1.704514051},
{"learn":[0.1751407536],"iteration":715,"passed_time":4.281386458,"remaining_time":1.698203567},
{"learn":[0.1750691298],"iteration":716,"passed_time":4.287005271,"remaining_time":1.692081579},
{"learn":[0.1749973318],"iteration":717,"passed_time":4.298353853,"remaining_time":1.688211402},
{"learn":[0.1749070708],"iteration":718,"passed_time":4.315284749,"remaining_time":1.686502106},
{"learn":[0.1748324587],"iteration":719,"passed_time":4.337289893,"remaining_time":1.686723847},
{"learn":[0.1747073405],"iteration":720,"passed_time":4.343222988,"remaining_time":1.680664651},
{"learn":[0.174593066],"iteration":721,"passed_time":4.348908758,"remaining_time":1.674510574},
{"learn":[0.1745157641],"iteration":722,"passed_time":4.354576819,"remaining_time":1.668351008},
{"learn":[0.1744639446],"iteration":723,"passed_time":4.359948016,"remaining_time":1.66207963},
{"learn":[0.1743285132],"iteration":724,"passed_time":4.365379961,"remaining_time":1.655833778},
{"learn":[0.1742223157],"iteration":725,"passed_time":4.371222267,"remaining_time":1.649745043},
{"learn":[0.1741666716],"iteration":726,"passed_time":4.377093863,"remaining_time":1.643667984},
{"learn":[0.1740723473],"iteration":727,"passed_time":4.382923253,"remaining_time":1.637575721},
{"learn":[0.1739634528],"iteration":728,"passed_time":4.388584357,"remaining_time":1.63142162},
{"learn":[0.1738595125],"iteration":729,"passed_time":4.393507443,"remaining_time":1.624995904},
{"learn":[0.1737594647],"iteration":730,"passed_time":4.398285785,"remaining_time":1.618521034},
{"learn":[0.1736969723],"iteration":731,"passed_time":4.403925389,"remaining_time":1.612366126},
{"learn":[0.1736152303],"iteration":732,"passed_time":4.409683823,"remaining_time":1.606255908},
{"learn":[0.1735082484],"iteration":733,"passed_time":4.41462745,"remaining_time":1.599851365},
{"learn":[0.1734464327],"iteration":734,"passed_time":4.420221223,"remaining_time":1.593685203},
{"learn":[0.1733401321],"iteration":735,"passed_time":4.425069854,"remaining_time":1.587253317},
{"learn":[0.1732343979],"iteration":736,"passed_time":4.429950192,"remaining_time":1.580837043},
{"learn":[0.1731107992],"iteration":737,"passed_time":4.436891378,"remaining_time":1.57515656},
{"learn":[0.1730054653],"iteration":738,"passed_time":4.44275385,"remaining_time":1.569091684},
{"learn":[0.1729410705],"iteration":739,"passed_time":4.448132338,"remaining_time":1.562857308},
{"learn":[0.1728740435],"iteration":740,"passed_time":4.453177129,"remaining_time":1.556508605},
{"learn":[0.1727890413],"iteration":741,"passed_time":4.457824183,"remaining_time":1.55002512},
{"learn":[0.1727226075],"iteration":742,"passed_time":4.463013219,"remaining_time":1.543734047},
{"learn":[0.1726339508],"iteration":743,"passed_time":4.469085017,"remaining_time":1.537749683},
{"learn":[0.1725768964],"iteration":744,"passed_time":4.474342467,"remaining_time":1.531486348},
{"learn":[0.1725032497],"iteration":745,"passed_time":4.479071769,"remaining_time":1.525045884},
{"learn":[0.1724151575],"iteration":746,"passed_time":4.484213931,"remaining_time":1.518749832},
{"learn":[0.1723114515],"iteration":747,"passed_time":4.489758539,"remaining_time":1.512592449},
{"learn":[0.1722594065],"iteration":748,"passed_time":4.495179776,"remaining_time":1.506395359},
{"learn":[0.1721858768],"iteration":749,"passed_time":4.499878161,"remaining_time":1.499959387},
{"learn":[0.172118096],"iteration":750,"passed_time":4.504814789,"remaining_time":1.493607034},
{"learn":[0.1720508007],"iteration":751,"passed_time":4.509971784,"remaining_time":1.48733112},
{"learn":[0.1719606085],"iteration":752,"passed_time":4.515325232,"remaining_time":1.481122619},
{"learn":[0.1718961557],"iteration":753,"passed_time":4.520340607,"remaining_time":1.474806087},
{"learn":[0.1717759773],"iteration":754,"passed_time":4.525276693,"remaining_time":1.468467271},
{"learn":[0.1716934677],"iteration":755,"passed_time":4.530023702,"remaining_time":1.462071142},
{"learn":[0.171622065],"iteration":756,"passed_time":4.536090542,"remaining_time":1.456103041},
{"learn":[0.171550882],"iteration":757,"passed_time":4.541801811,"remaining_time":1.450021159},
{"learn":[0.1714226299],"iteration":758,"passed_time":4.546736355,"remaining_time":1.443693625},
{"learn":[0.1712975125],"iteration":759,"passed_time":4.551573778,"remaining_time":1.437339088},
{"learn":[0.1712222752],"iteration":760,"passed_time":4.556262039,"remaining_time":1.430941692},
{"learn":[0.1711458395],"iteration":761,"passed_time":4.561939475,"remaining_time":1.424857736},
{"learn":[0.171034247],"iteration":762,"passed_time":4.56758358,"remaining_time":1.418764493},
{"learn":[0.1709705007],"iteration":763,"passed_time":4.572260549,"remaining_time":1.412373678},
{"learn":[0.1708620461],"iteration":764,"passed_time":4.577001225,"remaining_time":1.406006912},
{"learn":[0.1707401257],"iteration":765,"passed_time":4.581948228,"remaining_time":1.399707422},
{"learn":[0.1706775068],"iteration":766,"passed_time":4.5865352,"remaining_time":1.393302088},
{"learn":[0.1706170609],"iteration":767,"passed_time":4.591523201,"remaining_time":1.387022634},
{"learn":[0.170533169],"iteration":768,"passed_time":4.596657781,"remaining_time":1.380790569},
{"learn":[0.1704043749],"iteration":769,"passed_time":4.602206847,"remaining_time":1.374685162},
{"learn":[0.1703093059],"iteration":770,"passed_time":4.606538703,"remaining_time":1.368219667},
{"learn":[0.1702202706],"iteration":771,"passed_time":4.611101676,"remaining_time":1.361827956},
{"learn":[0.1701607945],"iteration":772,"passed_time":4.616071886,"remaining_time":1.355560567},
{"learn":[0.1700730709],"iteration":773,"passed_time":4.621612619,"remaining_time":1.349463116},
{"learn":[0.1700024757],"iteration":774,"passed_time":4.626873736,"remaining_time":1.343285923},
{"learn":[0.1699322249],"iteration":775,"passed_time":4.631675118,"remaining_time":1.336978385},
{"learn":[0.1698514665],"iteration":776,"passed_time":4.636599205,"remaining_time":1.330709939},
{"learn":[0.1697516466],"iteration":777,"passed_time":4.641340422,"remaining_time":1.324392768},
{"learn":[0.1696726825],"iteration":778,"passed_time":4.646340214,"remaining_time":1.318153001},
{"learn":[0.1695348022],"iteration":779,"passed_time":4.651521876,"remaining_time":1.311967709},
{"learn":[0.1694243614],"iteration":780,"passed_time":4.656527834,"remaining_time":1.305735718},
{"learn":[0.169346378],"iteration":781,"passed_time":4.661874324,"remaining_time":1.299601794},
{"learn":[0.1692777701],"iteration":782,"passed_time":4.666762203,"remaining_time":1.293342782},
{"learn":[0.1692368643],"iteration":783,"passed_time":4.671200014,"remaining_time":1.286963269},
{"learn":[0.169177827],"iteration":784,"passed_time":4.67628122,"remaining_time":1.28076492},
{"learn":[0.1691117878],"iteration":785,"passed_time":4.6814153,"remaining_time":1.274583809},
{"learn":[0.1690233532],"iteration":786,"passed_time":4.686860161,"remaining_time":1.268489472},
{"learn":[0.1689477212],"iteration":787,"passed_time":4.691644335,"remaining_time":1.262219034},
{"learn":[0.1688452015],"iteration":788,"passed_time":4.696590879,"remaining_time":1.255995786},
{"learn":[0.1687836346],"iteration":789,"passed_time":4.701748458,"remaining_time":1.249831869},
{"learn":[0.1687177452],"iteration":790,"passed_time":4.707154487,"remaining_time":1.243736141},
{"learn":[0.1686137364],"iteration":791,"passed_time":4.712420812,"remaining_time":1.237605466},
{"learn":[0.1685368095],"iteration":792,"passed_time":4.717138364,"remaining_time":1.231333722},
{"learn":[0.1684445214],"iteration":793,"passed_time":4.721805709,"remaining_time":1.225052866},
{"learn":[0.1683619984],"iteration":794,"passed_time":4.726863207,"remaining_time":1.218876676},
{"learn":[0.1682738501],"iteration":795,"passed_time":4.731621924,"remaining_time":1.212626724},
{"learn":[0.1681771988],"iteration":796,"passed_time":4.736310894,"remaining_time":1.20636275},
{"learn":[0.1680746951],"iteration":797,"passed_time":4.741213314,"remaining_time":1.200156754},
{"learn":[0.1679980339],"iteration":798,"passed_time":4.746217023,"remaining_time":1.193979501},
{"learn":[0.1679073603],"iteration":799,"passed_time":4.751754464,"remaining_time":1.187938616},
{"learn":[0.1678303455],"iteration":800,"passed_time":4.756925876,"remaining_time":1.181808052},
{"learn":[0.167740192],"iteration":801,"passed_time":4.761634261,"remaining_time":1.175565566},
{"learn":[0.1676730068],"iteration":802,"passed_time":4.766276565,"remaining_time":1.169310689},
{"learn":[0.1676082596],"iteration":803,"passed_time":4.770912578,"remaining_time":1.16305829},
{"learn":[0.1675240598],"iteration":804,"passed_time":4.776352481,"remaining_time":1.157004638},
{"learn":[0.1674482037],"iteration":805,"passed_time":4.782029292,"remaining_time":1.151009532},
{"learn":[0.1673615067],"iteration":806,"passed_time":4.787543734,"remaining_time":1.144976382},
{"learn":[0.1673125903],"iteration":807,"passed_time":4.793139548,"remaining_time":1.138963853},
{"learn":[0.1671778188],"iteration":808,"passed_time":4.798267336,"remaining_time":1.132841856},
{"learn":[0.1671058146],"iteration":809,"passed_time":4.803184131,"remaining_time":1.126672821},
{"learn":[0.1669886003],"iteration":810,"passed_time":4.807928099,"remaining_time":1.120466598},
{"learn":[0.1668896015],"iteration":811,"passed_time":4.812894934,"remaining_time":1.114315576},
{"learn":[0.1668177094],"iteration":812,"passed_time":4.817673609,"remaining_time":1.108124188},
{"learn":[0.1667576522],"iteration":813,"passed_time":4.823296505,"remaining_time":1.102129177},
{"learn":[0.1666669931],"iteration":814,"passed_time":4.828327588,"remaining_time":1.096000741},
{"learn":[0.1666017264],"iteration":815,"passed_time":4.833165052,"remaining_time":1.089831335},
{"learn":[0.1665484021],"iteration":816,"passed_time":4.838133387,"remaining_time":1.083694504},
{"learn":[0.1664797182],"iteration":817,"passed_time":4.843114889,"remaining_time":1.077563459},
{"learn":[0.1662683664],"iteration":818,"passed_time":4.849537009,"remaining_time":1.0717536},
{"learn":[0.1662318201],"iteration":819,"passed_time":4.854629798,"remaining_time":1.065650443},
{"learn":[0.1661048268],"iteration":820,"passed_time":4.859960204,"remaining_time":1.059601555},
{"learn":[0.1660102196],"iteration":821,"passed_time":4.864790044,"remaining_time":1.053446019},
{"learn":[0.1659320087],"iteration":822,"passed_time":4.869859042,"remaining_time":1.04734514},
{"learn":[0.1658606917],"iteration":823,"passed_time":4.875349318,"remaining_time":1.041336748},
{"learn":[0.165768422],"iteration":824,"passed_time":4.880676891,"remaining_time":1.035295098},
{"learn":[0.1657283487],"iteration":825,"passed_time":4.885136702,"remaining_time":1.02907238},
{"learn":[0.165660379],"iteration":826,"passed_time":4.88986842,"remaining_time":1.022910806},
{"learn":[0.165586272],"iteration":827,"passed_time":4.894436476,"remaining_time":1.016718688},
{"learn":[0.1655191477],"iteration":828,"passed_time":4.899415686,"remaining_time":1.010615298},
{"learn":[0.1654545591],"iteration":829,"passed_time":4.904140029,"remaining_time":1.004462416},
{"learn":[0.1653556762],"iteration":830,"passed_time":4.909717094,"remaining_time":0.9984863885},
{"learn":[0.1652986753],"iteration":831,"passed_time":4.915397447,"remaining_time":0.9925321768},
{"learn":[0.1652052327],"iteration":832,"passed_time":4.920131831,"remaining_time":0.9863889746},
{"learn":[0.1651369216],"iteration":833,"passed_time":4.924951755,"remaining_time":0.9802661766},
{"learn":[0.1650571762],"iteration":834,"passed_time":4.930005837,"remaining_time":0.9741927701},
{"learn":[0.1649585057],"iteration":835,"passed_time":4.934863134,"remaining_time":0.9680831985},
{"learn":[0.1648967476],"iteration":836,"passed_time":4.939824011,"remaining_time":0.9619967906},
{"learn":[0.164803939],"iteration":837,"passed_time":4.944647976,"remaining_time":0.9558866015},
{"learn":[0.1646759905],"iteration":838,"passed_time":4.950167292,"remaining_time":0.9499129131},
{"learn":[0.16458913],"iteration":839,"passed_time":4.955235041,"remaining_time":0.9438542935},
{"learn":[0.1645101077],"iteration":840,"passed_time":4.960752191,"remaining_time":0.9378829945},
{"learn":[0.1644303044],"iteration":841,"passed_time":4.965922561,"remaining_time":0.9318477014},
{"learn":[0.1643590924],"iteration":842,"passed_time":4.970595739,"remaining_time":0.9257218636},
{"learn":[0.1642695756],"iteration":843,"passed_time":4.975393121,"remaining_time":0.9196224253},
{"learn":[0.16414974],"iteration":844,"passed_time":4.981325174,"remaining_time":0.9137342036},
{"learn":[0.1640563402],"iteration":845,"passed_time":4.986868115,"remaining_time":0.907775047},
{"learn":[0.1639968552],"iteration":846,"passed_time":4.991604291,"remaining_time":0.9016711412},
{"learn":[0.163927222],"iteration":847,"passed_time":4.996622708,"remaining_time":0.8956210514},
{"learn":[0.1638093463],"iteration":848,"passed_time":5.001670915,"remaining_time":0.8895786905},
{"learn":[0.1637027828],"iteration":849,"passed_time":5.006412841,"remaining_time":0.883484619},
{"learn":[0.1636193861],"iteration":850,"passed_time":5.012117319,"remaining_time":0.8775622567},
{"learn":[0.163529982],"iteration":851,"passed_time":5.017439225,"remaining_time":0.8715739499},
{"learn":[0.1634700989],"iteration":852,"passed_time":5.02301504,"remaining_time":0.8656309623},
{"learn":[0.1633190705],"iteration":853,"passed_time":5.029181627,"remaining_time":0.8597898332},
{"learn":[0.1632348219],"iteration":854,"passed_time":5.035499125,"remaining_time":0.8539735359},
{"learn":[0.1631798476],"iteration":855,"passed_time":5.04104115,"remaining_time":0.848025614},
{"learn":[0.1631235162],"iteration":856,"passed_time":5.04794792,"remaining_time":0.8423063624},
{"learn":[0.1630509367],"iteration":857,"passed_time":5.055174972,"remaining_time":0.8366373497},
{"learn":[0.1629975854],"iteration":858,"passed_time":5.061337559,"remaining_time":0.8307899835},
{"learn":[0.1629318789],"iteration":859,"passed_time":5.066875709,"remaining_time":0.8248402316},
{"learn":[0.1627867955],"iteration":860,"passed_time":5.072351568,"remaining_time":0.8188813798},
{"learn":[0.1627214468],"iteration":861,"passed_time":5.077100994,"remaining_time":0.8128073517},
{"learn":[0.1626579731],"iteration":862,"passed_time":5.081985748,"remaining_time":0.8067578766},
{"learn":[0.1625741534],"iteration":863,"passed_time":5.087044872,"remaining_time":0.8007385447},
{"learn":[0.1623627232],"iteration":864,"passed_time":5.091978833,"remaining_time":0.7947018988},
{"learn":[0.1622818081],"iteration":865,"passed_time":5.097092747,"remaining_time":0.7886956444},
{"learn":[0.1622027106],"iteration":866,"passed_time":5.102260284,"remaining_time":0.7826996744},
{"learn":[0.1620741168],"iteration":867,"passed_time":5.107914721,"remaining_time":0.776779658},
{"learn":[0.1619676363],"iteration":868,"passed_time":5.113282168,"remaining_time":0.7708169896},
{"learn":[0.1618526887],"iteration":869,"passed_time":5.118967729,"remaining_time":0.7649032238},
{"learn":[0.1617785966],"iteration":870,"passed_time":5.123700113,"remaining_time":0.7588488113},
{"learn":[0.1616988113],"iteration":871,"passed_time":5.128371375,"remaining_time":0.7527884587},
{"learn":[0.1616262131],"iteration":872,"passed_time":5.13307626,"remaining_time":0.7467361799},
{"learn":[0.1614856638],"iteration":873,"passed_time":5.137824894,"remaining_time":0.7406932914},
{"learn":[0.1614081069],"iteration":874,"passed_time":5.142505656,"remaining_time":0.7346436651},
{"learn":[0.161316424],"iteration":875,"passed_time":5.147787438,"remaining_time":0.7286822402},
{"learn":[0.1612199469],"iteration":876,"passed_time":5.153259923,"remaining_time":0.7227491113},
{"learn":[0.1611372744],"iteration":877,"passed_time":5.15864187,"remaining_time":0.7168044511},
{"learn":[0.1610426409],"iteration":878,"passed_time":5.163838489,"remaining_time":0.7108355599},
{"learn":[0.1609823098],"iteration":879,"passed_time":5.168817823,"remaining_time":0.7048387941},
{"learn":[0.1608858936],"iteration":880,"passed_time":5.173526,"remaining_time":0.6988077118},
{"learn":[0.1608413602],"iteration":881,"passed_time":5.17840038,"remaining_time":0.6928018649},
{"learn":[0.1607429111],"iteration":882,"passed_time":5.18378891,"remaining_time":0.6868667072},
{"learn":[0.1606858014],"iteration":883,"passed_time":5.189161565,"remaining_time":0.680930703},
{"learn":[0.1605818864],"iteration":884,"passed_time":5.194542761,"remaining_time":0.6749970819},
{"learn":[0.1605051023],"iteration":885,"passed_time":5.19924998,"remaining_time":0.6689779883},
{"learn":[0.1604293314],"iteration":886,"passed_time":5.204612968,"remaining_time":0.663045395},
{"learn":[0.1603425647],"iteration":887,"passed_time":5.209418809,"remaining_time":0.6570438137},
{"learn":[0.1602608422],"iteration":888,"passed_time":5.214455933,"remaining_time":0.6510738004},
{"learn":[0.1601995494],"iteration":889,"passed_time":5.219999291,"remaining_time":0.6451684517},
{"learn":[0.1601302334],"iteration":890,"passed_time":5.225256741,"remaining_time":0.6392289391},
{"learn":[0.1600715591],"iteration":891,"passed_time":5.230272533,"remaining_time":0.6332616968},
{"learn":[0.1600110837],"iteration":892,"passed_time":5.234809591,"remaining_time":0.6272392231},
{"learn":[0.1599327612],"iteration":893,"passed_time":5.23983084,"remaining_time":0.6212774822},
{"learn":[0.1598587324],"iteration":894,"passed_time":5.245188788,"remaining_time":0.6153573438},
{"learn":[0.1598077168],"iteration":895,"passed_time":5.250169872,"remaining_time":0.6093947173},
{"learn":[0.1596623393],"iteration":896,"passed_time":5.255127249,"remaining_time":0.603431557},
{"learn":[0.1596196835],"iteration":897,"passed_time":5.260269703,"remaining_time":0.597491659},
{"learn":[0.1595699815],"iteration":898,"passed_time":5.265562111,"remaining_time":0.5915703818},
{"learn":[0.1595250893],"iteration":899,"passed_time":5.270350744,"remaining_time":0.5855945271},
{"learn":[0.1594608039],"iteration":900,"passed_time":5.275185125,"remaining_time":0.5796263345},
{"learn":[0.1593324985],"iteration":901,"passed_time":5.28807928,"remaining_time":0.5745363298},
{"learn":[0.1592557278],"iteration":902,"passed_time":5.304861098,"remaining_time":0.5698466517},
{"learn":[0.1591511855],"iteration":903,"passed_time":5.311605874,"remaining_time":0.5640643406},
{"learn":[0.1590979304],"iteration":904,"passed_time":5.317583634,"remaining_time":0.558199387},
{"learn":[0.1589972963],"iteration":905,"passed_time":5.32381326,"remaining_time":0.5523603162},
{"learn":[0.1589068941],"iteration":906,"passed_time":5.32988485,"remaining_time":0.5465041798},
{"learn":[0.1588240361],"iteration":907,"passed_time":5.335850944,"remaining_time":0.5406368798},
{"learn":[0.1587481211],"iteration":908,"passed_time":5.341167809,"remaining_time":0.5347043681},
{"learn":[0.1586708495],"iteration":909,"passed_time":5.346754082,"remaining_time":0.5287998542},
{"learn":[0.1586080311],"iteration":910,"passed_time":5.352475142,"remaining_time":0.522909207},
{"learn":[0.1585426936],"iteration":911,"passed_time":5.359511825,"remaining_time":0.5171458778},
{"learn":[0.1584315787],"iteration":912,"passed_time":5.364138629,"remaining_time":0.5111501213},
{"learn":[0.1583646806],"iteration":913,"passed_time":5.368904888,"remaining_time":0.5051704818},
{"learn":[0.1582657749],"iteration":914,"passed_time":5.375180596,"remaining_time":0.4993337166},
{"learn":[0.1581999263],"iteration":915,"passed_time":5.380727579,"remaining_time":0.4934291666},
{"learn":[0.158014629],"iteration":916,"passed_time":5.385940239,"remaining_time":0.4874951361},
{"learn":[0.1579268881],"iteration":917,"passed_time":5.390937364,"remaining_time":0.4815434247},
{"learn":[0.1578531143],"iteration":918,"passed_time":5.396152983,"remaining_time":0.4756130486},
{"learn":[0.1577918776],"iteration":919,"passed_time":5.401859085,"remaining_time":0.469726877},
{"learn":[0.1577025367],"iteration":920,"passed_time":5.408211999,"remaining_time":0.4638965776},
{"learn":[0.157624071],"iteration":921,"passed_time":5.413597904,"remaining_time":0.4579833368},
{"learn":[0.157511681],"iteration":922,"passed_time":5.418663652,"remaining_time":0.45204453},
{"learn":[0.1573914937],"iteration":923,"passed_time":5.424202052,"remaining_time":0.4461464891},
{"learn":[0.1572909789],"iteration":924,"passed_time":5.428825898,"remaining_time":0.4401750728},
{"learn":[0.157157915],"iteration":925,"passed_time":5.43549351,"remaining_time":0.4343698917},
{"learn":[0.157108906],"iteration":926,"passed_time":5.441984378,"remaining_time":0.4285489316},
{"learn":[0.1570545416],"iteration":927,"passed_time":5.447928597,"remaining_time":0.4226841153},
{"learn":[0.1569918676],"iteration":928,"passed_time":5.453785944,"remaining_time":0.4168124887},
{"learn":[0.1569212195],"iteration":929,"passed_time":5.459360259,"remaining_time":0.4109195894},
{"learn":[0.156816285],"iteration":930,"passed_time":5.464226473,"remaining_time":0.4049748943},
{"learn":[0.1567280835],"iteration":931,"passed_time":5.47032602,"remaining_time":0.3991224993},
{"learn":[0.1566899515],"iteration":932,"passed_time":5.475870336,"remaining_time":0.3932297026},
{"learn":[0.156622987],"iteration":933,"passed_time":5.480961792,"remaining_time":0.3873056512},
{"learn":[0.1565756225],"iteration":934,"passed_time":5.486217909,"remaining_time":0.3813948279},
{"learn":[0.1565140156],"iteration":935,"passed_time":5.492358913,"remaining_time":0.3755459086},
{"learn":[0.1564359374],"iteration":936,"passed_time":5.498083765,"remaining_time":0.3696683855},
{"learn":[0.1563758844],"iteration":937,"passed_time":5.503696204,"remaining_time":0.3637837576},
{"learn":[0.156312689],"iteration":938,"passed_time":5.508543126,"remaining_time":0.3578499794},
{"learn":[0.156228374],"iteration":939,"passed_time":5.51418198,"remaining_time":0.3519690626},
{"learn":[0.1561487883],"iteration":940,"passed_time":5.520697597,"remaining_time":0.3461436326},
{"learn":[0.1560873502],"iteration":941,"passed_time":5.526858476,"remaining_time":0.3402948956},
{"learn":[0.1559994379],"iteration":942,"passed_time":5.533236306,"remaining_time":0.3344586102},
{"learn":[0.1559412933],"iteration":943,"passed_time":5.538077062,"remaining_time":0.3285299952},
{"learn":[0.1558739584],"iteration":944,"passed_time":5.543443509,"remaining_time":0.3226342783},
{"learn":[0.155815239],"iteration":945,"passed_time":5.549391603,"remaining_time":0.3167728822},
{"learn":[0.155731979],"iteration":946,"passed_time":5.557575498,"remaining_time":0.3110364323},
{"learn":[0.1556393007],"iteration":947,"passed_time":5.562632497,"remaining_time":0.3051233015},
{"learn":[0.1555878807],"iteration":948,"passed_time":5.570756477,"remaining_time":0.299376797},
{"learn":[0.1555425913],"iteration":949,"passed_time":5.578086317,"remaining_time":0.2935834904},
{"learn":[0.1554709536],"iteration":950,"passed_time":5.584839717,"remaining_time":0.2877572515},
{"learn":[0.1554077185],"iteration":951,"passed_time":5.590928974,"remaining_time":0.2818955785},
{"learn":[0.155354513],"iteration":952,"passed_time":5.597333344,"remaining_time":0.2760489687},
{"learn":[0.1552921116],"iteration":953,"passed_time":5.603518889,"remaining_time":0.2701906382},
{"learn":[0.155185128],"iteration":954,"passed_time":5.609982966,"remaining_time":0.2643447471},
{"learn":[0.1551082509],"iteration":955,"passed_time":5.615916394,"remaining_time":0.2584731395},
{"learn":[0.1549987221],"iteration":956,"passed_time":5.621313965,"remaining_time":0.2525773255},
{"learn":[0.1549147864],"iteration":957,"passed_time":5.627044149,"remaining_time":0.2466971339},
{"learn":[0.1548571561],"iteration":958,"passed_time":5.632629006,"remaining_time":0.2408110419},
{"learn":[0.1547996301],"iteration":959,"passed_time":5.637575008,"remaining_time":0.2348989587},
{"learn":[0.1547469132],"iteration":960,"passed_time":5.642904623,"remaining_time":0.229004454},
{"learn":[0.1546895587],"iteration":961,"passed_time":5.648137282,"remaining_time":0.2231072939},
{"learn":[0.1545744575],"iteration":962,"passed_time":5.653317819,"remaining_time":0.2172095112},
{"learn":[0.154515582],"iteration":963,"passed_time":5.65859581,"remaining_time":0.211316856},
{"learn":[0.1544520936],"iteration":964,"passed_time":5.664139709,"remaining_time":0.205435119},
{"learn":[0.154380929],"iteration":965,"passed_time":5.669589112,"remaining_time":0.1995507555},
{"learn":[0.1543119714],"iteration":966,"passed_time":5.675091179,"remaining_time":0.1936690888},
{"learn":[0.1542219185],"iteration":967,"passed_time":5.680704076,"remaining_time":0.1877918703},
{"learn":[0.1541729095],"iteration":968,"passed_time":5.685770158,"remaining_time":0.1818977037},
{"learn":[0.1540937148],"iteration":969,"passed_time":5.691150021,"remaining_time":0.1760149491},
{"learn":[0.1539883566],"iteration":970,"passed_time":5.695898655,"remaining_time":0.1701143779},
{"learn":[0.1539425556],"iteration":971,"passed_time":5.700710287,"remaining_time":0.1642179918},
{"learn":[0.1538627957],"iteration":972,"passed_time":5.706393723,"remaining_time":0.1583480273},
{"learn":[0.1537736975],"iteration":973,"passed_time":5.711931331,"remaining_time":0.152474553},
{"learn":[0.1537419553],"iteration":974,"passed_time":5.716768503,"remaining_time":0.1465838078},
{"learn":[0.1536936377],"iteration":975,"passed_time":5.722241905,"remaining_time":0.1407108665},
{"learn":[0.1536194757],"iteration":976,"passed_time":5.727222406,"remaining_time":0.1348271396},
{"learn":[0.1535877805],"iteration":977,"passed_time":5.731991415,"remaining_time":0.1289405022},
{"learn":[0.1535150146],"iteration":978,"passed_time":5.736588095,"remaining_time":0.1230524515},
{"learn":[0.1534591051],"iteration":979,"passed_time":5.741486683,"remaining_time":0.1171731976},
{"learn":[0.1533875808],"iteration":980,"passed_time":5.747058873,"remaining_time":0.1113089894},
{"learn":[0.1533360161],"iteration":981,"passed_time":5.752123329,"remaining_time":0.1054360692},
{"learn":[0.153274696],"iteration":982,"passed_time":5.757319157,"remaining_time":0.09956706578},
{"learn":[0.1531942659],"iteration":983,"passed_time":5.762221411,"remaining_time":0.09369465708},
{"learn":[0.1531027658],"iteration":984,"passed_time":5.768004094,"remaining_time":0.08783762579},
{"learn":[0.1529947838],"iteration":985,"passed_time":5.773551409,"remaining_time":0.08197740338},
{"learn":[0.1529264231],"iteration":986,"passed_time":5.779036977,"remaining_time":0.07611700173},
{"learn":[0.152860535],"iteration":987,"passed_time":5.784536086,"remaining_time":0.07025752332},
{"learn":[0.1527954671],"iteration":988,"passed_time":5.789104726,"remaining_time":0.06438842466},
{"learn":[0.1527446552],"iteration":989,"passed_time":5.79397769,"remaining_time":0.05852502717},
{"learn":[0.1526537413],"iteration":990,"passed_time":5.799346928,"remaining_time":0.05266813557},
{"learn":[0.1525725901],"iteration":991,"passed_time":5.804637502,"remaining_time":0.04681159276},
{"learn":[0.1525031843],"iteration":992,"passed_time":5.809979991,"remaining_time":0.04095655583},
{"learn":[0.1524523175],"iteration":993,"passed_time":5.814785915,"remaining_time":0.03509931136},
{"learn":[0.1523809008],"iteration":994,"passed_time":5.819439969,"remaining_time":0.02924341693},
{"learn":[0.1522593558],"iteration":995,"passed_time":5.824518925,"remaining_time":0.02339164227},
{"learn":[0.1520892268],"iteration":996,"passed_time":5.829448512,"remaining_time":0.01754096844},
{"learn":[0.1520084335],"iteration":997,"passed_time":5.834093107,"remaining_time":0.01169156935},
{"learn":[0.1519258562],"iteration":998,"passed_time":5.839486428,"remaining_time":0.00584533176},
{"learn":[0.1518159272],"iteration":999,"passed_time":5.844990121,"remaining_time":0}
]}